Workbook

Sheet ACTUALS
A1: Historical Actuals
A3: Year | B3: Product Line | C3: Policies in Force | D3: Avg Premium | E3: Gross Written Premium | F3: Claims Paid | G3: Net Earned Premium | H3: Operating expense | I3: Underwriting Income | J3: Loss Ratio | K3: Expense Ratio | L3: Combined Ratio | M3: Policy Growth Rate | N3: Premium Growth rate | O3: GWP Growth | P3: Cost per policy
A4: 2019 | B4: Accident & Health | C4: 185000 | D4: 445 | E4: =C4*D4 -> 82325000 | F4: 44455500 | G4: =E4*0.97 -> 79855250 | H4: =G4*K4 -> 30504706 | I4: =G4-F4-H4 -> 4895044.5 | J4: =F4/G4 -> 0.55670103 | K4: 0.382 | L4: =J4+K4 -> 0.93870103 | M4: - | N4: - | O4: - | P4: =H4/C4 -> 164.8903
A5: 2020 | B5: Accident & Health | C5: 172000 | D5: 448 | E5: =C5*D5 -> 77056000 | F5: 44292160 | G5: =E5*0.97 -> 74744320 | H5: =G5*K5 -> 29972472 | I5: =G5-F5-H5 -> 479687.68 | J5: =F5/G5 -> 0.59258229 | K5: 0.401 | L5: =J5+K5 -> 0.99358229 | M5: =((C5-C4)/C4) -> -0.07027027 | N5: =((G5-G4)/G4) -> -0.064002429 | O5: =((E5-E4)/E4) -> -0.064002429 | P5: =H5/C5 -> 174.25856 | Q5: =((P5-P4)/P4) -> 0.056815107 | R5: =AVERAGE(Q5:Q9) -> -0.0023212917
A6: 2021 | B6: Accident & Health | C6: 178000 | D6: 452 | E6: =C6*D6 -> 80456000 | F6: 43446240 | G6: =E6*0.97 -> 78042320 | H6: =G6*K6 -> 29499997 | I6: =G6-F6-H6 -> 5096083 | J6: =F6/G6 -> 0.55670103 | K6: 0.378 | L6: =J6+K6 -> 0.93470103 | M6: =((C6-C5)/C5) -> 0.034883721 | N6: =((G6-G5)/G5) -> 0.044123754 | O6: =((E6-E5)/E5) -> 0.044123754 | P6: =H6/C6 -> 165.73032 | Q6: =((P6-P5)/P5) -> -0.04894015
A7: 2022 | B7: Accident & Health | C7: 188000 | D7: 458 | E7: =C7*D7 -> 86104000 | F7: 45634120 | G7: =E7*0.97 -> 83520880 | H7: =G7*K7 -> 30819205 | I7: =G7-F7-H7 -> 7067555.3 | J7: =F7/G7 -> 0.54637978 | K7: 0.369 | L7: =J7+K7 -> 0.91537978 | M7: =((C7-C6)/C6) -> 0.056179775 | N7: =((G7-G6)/G6) -> 0.070199861 | O7: =((E7-E6)/E6) -> 0.070199861 | P7: =H7/C7 -> 163.93194 | Q7: =((P7-P6)/P6) -> -0.010851243
A8: 2023 | B8: Accident & Health | C8: 196000 | D8: 463 | E8: =C8*D8 -> 90748000 | F8: 47188960 | G8: =E8*0.97 -> 88025560 | H8: =G8*K8 -> 31865253 | I8: =G8-F8-H8 -> 8971347.3 | J8: =F8/G8 -> 0.53608247 | K8: 0.362 | L8: =J8+K8 -> 0.89808247 | M8: =((C8-C7)/C7) -> 0.042553191 | N8: =((G8-G7)/G7) -> 0.053934777 | O8: =((E8-E7)/E7) -> 0.053934777 | P8: =H8/C8 -> 162.57782 | Q8: =((P8-P7)/P7) -> -0.0082602573
A9: 2024 | B9: Accident & Health | C9: 204000 | D9: 468 | E9: =C9*D9 -> 95472000 | F9: 48244800 | G9: =E9*0.97 -> 92607840 | H9: =G9*K9 -> 33153607 | I9: =G9-F9-H9 -> 11209433 | J9: =F9/G9 -> 0.52095805 | K9: 0.358 | L9: =J9+K9 -> 0.87895805 | M9: =((C9-C8)/C8) -> 0.040816327 | N9: =((G9-G8)/G8) -> 0.052056244 | O9: =((E9-E8)/E8) -> 0.052056244 | P9: =H9/C9 -> 162.51768 | Q9: =((P9-P8)/P8) -> -0.00036991516
A10: 2019 | B10: Life | C10: 142000 | D10: 375 | E10: =C10*D10 -> 53250000 | F10: 22365000 | G10: =E10*0.97 -> 51652500 | H10: =G10*K10 -> 20557695 | I10: =G10-F10-H10 -> 8729805 | J10: =F10/G10 -> 0.43298969 | K10: 0.398 | L10: =J10+K10 -> 0.83098969 | P10: =H10/C10 -> 144.7725
A11: 2020 | B11: Life | C11: 138000 | D11: 378 | E11: =C11*D11 -> 52164000 | F11: 23474000 | G11: =E11*0.97 -> 50599080 | H11: =G11*K11 -> 20846821 | I11: =G11-F11-H11 -> 6278259 | J11: =F11/G11 -> 0.46392148 | K11: 0.412 | L11: =J11+K11 -> 0.87592148 | M11: =((C11-C10)/C10) -> -0.028169014 | N11: =((G11-G10)/G10) -> -0.020394366 | O11: =((E11-E10)/E10) -> -0.020394366 | P11: =H11/C11 -> 151.06392 | Q11: =((P12-P11)/P11) -> -0.028663893 | R11: =AVERAGE(Q11:Q15) -> 0.062445767
A12: 2021 | B12: Life | C12: 144000 | D12: 382 | E12: =C12*D12 -> 55008000 | F12: 23695190 | G12: =E12*0.97 -> 53357760 | H12: =G12*K12 -> 21129673 | I12: =G12-F12-H12 -> 8532897 | J12: =F12/G12 -> 0.44408142 | K12: 0.396 | L12: =J12+K12 -> 0.84008142 | M12: =((C12-C11)/C11) -> 0.043478261 | N12: =((G12-G11)/G11) -> 0.054520359 | O12: =((E12-E11)/E11) -> 0.054520359 | P12: =H12/C12 -> 146.73384 | Q12: =((P13-P12)/P12) -> -0.0099423555
A13: 2022 | B13: Life | C13: 151000 | D13: 386 | E13: =C13*D13 -> 58286000 | F13: 24480120 | G13: =E13*0.97 -> 56537420 | H13: =G13*K13 -> 21936519 | I13: =G13-F13-H13 -> 10120781 | J13: =F13/G13 -> 0.43298969 | K13: 0.388 | L13: =J13+K13 -> 0.82098969 | M13: =((C13-C12)/C12) -> 0.048611111 | N13: =((G13-G12)/G12) -> 0.059591332 | O13: =((E13-E12)/E12) -> 0.059591332 | P13: =H13/C13 -> 145.27496 | Q13: =((P14-P13)/P13) -> -0.0078654986
A14: 2023 | B14: Life | C14: 158000 | D14: 390 | E14: =C14*D14 -> 61620000 | F14: 25280200 | G14: =E14*0.97 -> 59771400 | H14: =G14*K14 -> 22772903 | I14: =G14-F14-H14 -> 11718297 | J14: =F14/G14 -> 0.4229481 | K14: 0.381 | L14: =J14+K14 -> 0.8039481 | M14: =((C14-C13)/C13) -> 0.046357616 | N14: =((G14-G13)/G13) -> 0.0572007 | O14: =((E14-E13)/E13) -> 0.0572007 | P14: =H14/C14 -> 144.1323 | Q14: =((P15-P14)/P14) -> -0.0030015479
A15: 2024 | B15: Life | C15: 165000 | D15: 394 | E15: =C15*D15 -> 65010000 | F15: 26136000 | G15: =E15*0.97 -> 63059700 | H15: =G15*K15 -> 23710447 | I15: =G15-F15-H15 -> 13213253 | J15: =F15/G15 -> 0.41446439 | K15: 0.376 | L15: =J15+K15 -> 0.79046439 | M15: =((C15-C14)/C14) -> 0.044303797 | N15: =((G15-G14)/G14) -> 0.055014606 | O15: =((E15-E14)/E14) -> 0.055014606 | P15: =H15/C15 -> 143.69968 | Q15: =((P16-P15)/P15) -> 0.36170213
A16: 2019 | B16: Disability | C16: 98000 | D16: 512 | E16: =C16*D16 -> 50176000 | F16: 28599320 | G16: =E16*0.97 -> 48670720 | H16: =G16*K16 -> 19176264 | I16: =G16-F16-H16 -> 895136.32 | J16: =F16/G16 -> 0.58760832 | K16: 0.394 | L16: =J16+K16 -> 0.98160832 | P16: =H16/C16 -> 195.67616
A17: 2020 | B17: Disability | C17: 91000 | D17: 515 | E17: =C17*D17 -> 46865000 | F17: 28591650 | G17: =E17*0.97 -> 45459050 | H17: =G17*K17 -> 19001883 | I17: =G17-F17-H17 -> -2134482.9 | J17: =F17/G17 -> 0.62895397 | K17: 0.418 | L17: =J17+K17 -> 1.046954 | M17: =((C17-C16)/C16) -> -0.071428571 | N17: =((G17-G16)/G16) -> -0.065987723 | O17: =((E17-E16)/E16) -> -0.065987723 | P17: =H17/C17 -> 208.8119 | Q17: =((P17-P16)/P16) -> 0.067129997 | R17: =AVERAGE(Q17:Q21) -> -0.0055139812
A18: 2021 | B18: Disability | C18: 96000 | D18: 518 | E18: =C18*D18 -> 49728000 | F18: 27849680 | G18: =E18*0.97 -> 48236160 | H18: =G18*K18 -> 18908575 | I18: =G18-F18-H18 -> 1477905.3 | J18: =F18/G18 -> 0.57736105 | K18: 0.392 | L18: =J18+K18 -> 0.96936105 | M18: =((C18-C17)/C17) -> 0.054945055 | N18: =((G18-G17)/G17) -> 0.061090366 | O18: =((E18-E17)/E17) -> 0.061090366 | P18: =H18/C18 -> 196.96432 | Q18: =((P18-P17)/P17) -> -0.05673805
A19: 2022 | B19: Disability | C19: 103000 | D19: 522 | E19: =C19*D19 -> 53766000 | F19: 28479980 | G19: =E19*0.97 -> 52153020 | H19: =G19*K19 -> 19765995 | I19: =G19-F19-H19 -> 3907045.4 | J19: =F19/G19 -> 0.54608496 | K19: 0.379 | L19: =J19+K19 -> 0.92508496 | M19: =((C19-C18)/C18) -> 0.072916667 | N19: =((G19-G18)/G18) -> 0.081201737 | O19: =((E19-E18)/E18) -> 0.081201737 | P19: =H19/C19 -> 191.90286 | Q19: =((P19-P18)/P18) -> -0.025697345
A20: 2023 | B20: Disability | C20: 109000 | D20: 526 | E20: =C20*D20 -> 57334000 | F20: 29203340 | G20: =E20*0.97 -> 55613980 | H20: =G20*K20 -> 20632787 | I20: =G20-F20-H20 -> 5777853.4 | J20: =F20/G20 -> 0.5251079 | K20: 0.371 | L20: =J20+K20 -> 0.8961079 | M20: =((C20-C19)/C19) -> 0.058252427 | N20: =((G20-G19)/G19) -> 0.066361641 | O20: =((E20-E19)/E19) -> 0.066361641 | P20: =H20/C20 -> 189.29162 | Q20: =((P20-P19)/P19) -> -0.013607093
A21: 2024 | B21: Disability | C21: 115000 | D21: 531 | E21: =C21*D21 -> 61065000 | F21: 30088500 | G21: =E21*0.97 -> 59233050 | H21: =G21*K21 -> 21797762 | I21: =G21-F21-H21 -> 7346787.6 | J21: =F21/G21 -> 0.5079681 | K21: 0.368 | L21: =J21+K21 -> 0.8759681 | M21: =((C21-C20)/C20) -> 0.055045872 | N21: =((G21-G20)/G20) -> 0.065074825 | O21: =((E21-E20)/E20) -> 0.065074825 | P21: =H21/C21 -> 189.54576 | Q21: =((P21-P20)/P20) -> 0.0013425845
A23: YEAR TOTALS
A24: Year | B24: GWP | C24: Claims Paid | D24: Net Earned Premium | E24: Loss Ratio | F24: Operating Expense | G24: Expense ratio | H24: Combined Ratio | I24: Underwriting income | J24: Polices in force | K24: Avg premium
A25: 2019 | B25: {=SUMPRODUCT((A4:A21=2019)*E4:E21)} -> 185751000 | C25: {=SUMPRODUCT((A4:A21=2019)*F4:F21)} -> 95419820 | D25: {=SUMPRODUCT((A4:A21=2019)*G4:G21)} -> 180178470 | E25: =C25/D25 -> 0.52958503 | F25: =SUMIF($A$4:$A$21,2019,$H$4:$H$21) -> 70238664 | G25: =F25/D25 -> 0.38982829 | H25: =SUM(G25+E25) -> 0.91941331 | I25: =SUMIF($A$4:$A$21,2019,$I$4:$I$21) -> 14519986 | J25: =SUMIF($A$4:$A$21,2019,$C$4:$C$21) -> 425000 | K25: =B25/J25 -> 437.06118
A26: 2020 | B26: {=SUMPRODUCT((A4:A21=2020)*E4:E21)} -> 176085000 | C26: {=SUMPRODUCT((A4:A21=2020)*F4:F21)} -> 96357810 | D26: {=SUMPRODUCT((A4:A21=2020)*G4:G21)} -> 170802450 | E26: =C26/D26 -> 0.5641477 | F26: =SUMIF($A$4:$A$21,2020,$H$4:$H$21) -> 69821176 | G26: =F26/D26 -> 0.40878322 | H26: =SUM(G26+E26) -> 0.97293093 | I26: =SUMIF($A$4:$A$21,2020,$I$4:$I$21) -> 4623463.8 | J26: =SUMIF($A$4:$A$21,2020,$C$4:$C$21) -> 401000 | K26: =B26/J26 -> 439.11471
A27: 2021 | B27: {=SUMPRODUCT((A4:A21=2021)*E4:E21)} -> 185192000 | C27: {=SUMPRODUCT((A4:A21=2021)*F4:F21)} -> 94991110 | D27: {=SUMPRODUCT((A4:A21=2021)*G4:G21)} -> 179636240 | E27: =C27/D27 -> 0.52879703 | F27: =SUMIF($A$4:$A$21,2021,$H$4:$H$21) -> 69538245 | G27: =F27/D27 -> 0.38710588 | H27: =SUM(G27+E27) -> 0.91590291 | I27: =SUMIF($A$4:$A$21,2021,$I$4:$I$21) -> 15106885 | J27: =SUMIF($A$4:$A$21,2021,$C$4:$C$21) -> 418000 | K27: =B27/J27 -> 443.04306
A28: 2022 | B28: {=SUMPRODUCT((A4:A21=2022)*E4:E21)} -> 198156000 | C28: {=SUMPRODUCT((A4:A21=2022)*F4:F21)} -> 98594220 | D28: {=SUMPRODUCT((A4:A21=2022)*G4:G21)} -> 192211320 | E28: =C28/D28 -> 0.512947 | F28: =SUMIF($A$4:$A$21,2022,$H$4:$H$21) -> 72521718 | G28: =F28/D28 -> 0.37730201 | H28: =SUM(G28+E28) -> 0.89024901 | I28: =SUMIF($A$4:$A$21,2022,$I$4:$I$21) -> 21095382 | J28: =SUMIF($A$4:$A$21,2022,$C$4:$C$21) -> 442000 | K28: =B28/J28 -> 448.31674
A29: 2023 | B29: {=SUMPRODUCT((A4:A21=2023)*E4:E21)} -> 209702000 | C29: {=SUMPRODUCT((A4:A21=2023)*F4:F21)} -> 101672500 | D29: {=SUMPRODUCT((A4:A21=2023)*G4:G21)} -> 203410940 | E29: =C29/D29 -> 0.49983791 | F29: =SUMIF($A$4:$A$21,2023,$H$4:$H$21) -> 75270943 | G29: =F29/D29 -> 0.37004373 | H29: =SUM(G29+E29) -> 0.86988164 | I29: =SUMIF($A$4:$A$21,2023,$I$4:$I$21) -> 26467497 | J29: =SUMIF($A$4:$A$21,2023,$C$4:$C$21) -> 463000 | K29: =B29/J29 -> 452.92009
A30: 2024 | B30: {=SUMPRODUCT((A4:A21=2024)*E4:E21)} -> 221547000 | C30: {=SUMPRODUCT((A4:A21=2024)*F4:F21)} -> 104469300 | D30: {=SUMPRODUCT((A4:A21=2024)*G4:G21)} -> 214900590 | E30: =C30/D30 -> 0.48612849 | F30: =SUMIF($A$4:$A$21,2024,$H$4:$H$21) -> 78661816 | G30: =F30/D30 -> 0.36603816 | H30: =SUM(G30+E30) -> 0.85216665 | I30: =SUMIF($A$4:$A$21,2024,$I$4:$I$21) -> 31769474 | J30: =SUMIF($A$4:$A$21,2024,$C$4:$C$21) -> 484000 | K30: =B30/J30 -> 457.74174

Sheet ASSUMPTIONS
A1: MODEL ASSUMPTIONS
A3: Historical Data Growth rates (2019 -2024)
B4: BEAR | C4: BASE | D4: BULL
A5: Avg A&H Pol% | B5: =C5-1.5% -> 0.0058325488 | C5: 0.020832549 | D5: =C5+1.4% -> 0.034832549
A6: Avg Life Pol% | B6: =C6-1.5% -> 0.015916354 | C6: 0.030916354 | D6: =C6+1.4% -> 0.044916354
A7: Avg Disability Pol % | B7: =C7-1.5% -> 0.01894629 | C7: 0.03394629 | D7: =C7+1.4% -> 0.04794629
A9: Avg A&H Premium% | B9: =C9-1.5% -> 0.016262441 | C9: 0.031262441 | D9: =C9+1.4% -> 0.045262441
A10: Avg Life Premium% | B10: =C10-1.5% -> 0.026186526 | C10: 0.041186526 | D10: =C10+1.4% -> 0.055186526
A11: Avg Disability Premium% | B11: =C11-1.5% -> 0.026548169 | C11: 0.041548169 | D11: =C11+1.4% -> 0.055548169
A13: Avg A&H claims % | B13: =C13-1.5% -> 0.0018064103 | C13: 0.01680641 | D13: =C13+1.4% -> 0.03080641
A14: Avg Life claims % | B14: =C14-1.5% -> 0.016734146 | C14: 0.031734146 | D14: =C14+1.4% -> 0.045734146
A15: Avg Disability claims % | B15: =C15-1.5% -> -0.0045754858 | C15: 0.010424514 | D15: =C15+1.4% -> 0.024424514
A17: Avg A&H OPEX % | B17: =C17-1.5% -> -0.017321292 | C17: -0.0023212917 | D17: =C17+1.4% -> 0.011678708
A18: Avg Life claims OPEX % | B18: =C18-1.5% -> 0.047445767 | C18: 0.062445767 | D18: =C18+1.4% -> 0.076445767
A19: Avg Disability OPEX % | B19: =C19-1.5% -> -0.020513981 | C19: -0.0055139812 | D19: =C19+1.4% -> 0.0084860188
A22: Reinsurance Rate | B22: 0.03 | C22: 0.03 | D22: 0.03
A24: SCENARIO TOGGLE
A25: Active Scenario | B25: Base
A26: Avg A&H Pol% | B26: =IF($B$25="Base",C5,IF($B$25="Bear",B5,D5)) -> 0.020832549
A27: Avg Life Pol% | B27: =IF($B$25="Base",C6,IF($B$25="Bear",B6,D6)) -> 0.030916354
A28: Avg Disability Pol % | B28: =IF($B$25="Base",C7,IF($B$25="Bear",B7,D7)) -> 0.03394629
A29: Avg A&H Premium% | B29: =IF($B$25="Base",C9,IF($B$25="Bear",B9,D9)) -> 0.031262441
A30: Avg Life Premium% | B30: =IF($B$25="Base",C10,IF($B$25="Bear",B10,D10)) -> 0.041186526
A31: Avg Disability Premium% | B31: =IF($B$25="Base",C11,IF($B$25="Bear",B11,D11)) -> 0.041548169
A32: Avg A&H claims % | B32: =IF($B$25="Base",C13,IF($B$25="Bear",B13,D13)) -> 0.01680641
A33: Avg Life claims % | B33: =IF($B$25="Base",C14,IF($B$25="Bear",B14,D14)) -> 0.031734146
A34: Avg Disability claims % | B34: =IF($B$25="Base",C15,IF($B$25="Bear",B15,D15)) -> 0.010424514
A35: Reinsurance rate % | B35: =IF($B$25="Base",C22,IF($B$25="Bear",B22,D22)) -> 0.03
A36: Avg A&H OPEX % | B36: =IF($B$25="Base",C17,IF($B$25="Bear",B17,D17)) -> -0.0023212917
A37: Avg Life claims OPEX % | B37: =IF($B$25="Base",C18,IF($B$25="Bear",B18,D18)) -> 0.062445767
A38: Avg Disability OPEX % | B38: =IF($B$25="Base",C19,IF($B$25="Bear",B19,D19)) -> -0.0055139812

Sheet REVENUE
A1: COMBINED INSURANCE (CHUBB) — REVENUE FORECAST 2019-2026
B3: 2019 A | C3: 2020 A | D3: 2021 A | E3: 2022 A | F3: 2023 A | G3: 2024 A | H3: 2025 F | I3: 2026 F
A4: ACCIDENT & HEALTH
A5: Policies in Force | B5: 185000 | C5: 172000 | D5: 178000 | E5: 188000 | F5: 196000 | G5: 204000 | H5: =G5*(1+ASSUMPTIONS!$B$26) -> 208249.84 | I5: =H5*(1+ASSUMPTIONS!$B$26) -> 212588.21
A6: Avg Premium | B6: =ACTUALS!D4 -> 445 | C6: =ACTUALS!D5 -> 448 | D6: =ACTUALS!D6 -> 452 | E6: =ACTUALS!D7 -> 458 | F6: =ACTUALS!D8 -> 463 | G6: =ACTUALS!D9 -> 468 | H6: =G6*(1+ASSUMPTIONS!$B$29) -> 482.63082 | I6: =H6*(1+ASSUMPTIONS!$B$29) -> 497.71904
A7: Gross Written Premium | B7: =B5*B6 -> 82325000 | C7: =C5*C6 -> 77056000 | D7: =D5*D6 -> 80456000 | E7: =E5*E6 -> 86104000 | F7: =F5*F6 -> 90748000 | G7: =G5*G6 -> 95472000 | H7: =H5*H6 -> 1.0050779e+08 | I7: =I5*I6 -> 1.058092e+08
A8: Reinsurance Ceded | B8: =B7*(ASSUMPTIONS!$B$35) -> 2469750 | C8: =C7*(ASSUMPTIONS!$B$35) -> 2311680 | D8: =D7*(ASSUMPTIONS!$B$35) -> 2413680 | E8: =E7*(ASSUMPTIONS!$B$35) -> 2583120 | F8: =F7*(ASSUMPTIONS!$B$35) -> 2722440 | G8: =G7*(ASSUMPTIONS!$B$35) -> 2864160 | H8: =H7*(ASSUMPTIONS!$B$35) -> 3015233.7 | I8: =I7*(ASSUMPTIONS!$B$35) -> 3174276.1
A9: Net Earned Premium | B9: =B7-B8 -> 79855250 | C9: =C7-C8 -> 74744320 | D9: =D7-D8 -> 78042320 | E9: =E7-E8 -> 83520880 | F9: =F7-F8 -> 88025560 | G9: =G7-G8 -> 92607840 | H9: =H7-H8 -> 97492558 | I9: =I7-I8 -> 1.0263493e+08
A11: LIFE
A12: Policies in Force | B12: 142000 | C12: 138000 | D12: 144000 | E12: 151000 | F12: 158000 | G12: 165000 | H12: =G12*(1+ASSUMPTIONS!$B$27) -> 170101.2 | I12: =H12*(1+ASSUMPTIONS!$B$27) -> 175360.11
A13: Avg Premium | B13: 375 | C13: 378 | D13: 382 | E13: 386 | F13: 390 | G13: 394 | H13: =G13*(1+ASSUMPTIONS!$B$30) -> 410.22749 | I13: =H13*(1+ASSUMPTIONS!$B$30) -> 427.12334
A14: Gross Written Premium | B14: =B13*B12 -> 53250000 | C14: =C13*C12 -> 52164000 | D14: =D13*D12 -> 55008000 | E14: =E13*E12 -> 58286000 | F14: =F13*F12 -> 61620000 | G14: =G13*G12 -> 65010000 | H14: =H13*H12 -> 69780188 | I14: =I13*I12 -> 74900394
A15: Reinsurance Ceded | B15: =B14*ASSUMPTIONS!$B$35 -> 1597500 | C15: =C14*ASSUMPTIONS!$B$35 -> 1564920 | D15: =D14*ASSUMPTIONS!$B$35 -> 1650240 | E15: =E14*ASSUMPTIONS!$B$35 -> 1748580 | F15: =F14*ASSUMPTIONS!$B$35 -> 1848600 | G15: =G14*ASSUMPTIONS!$B$35 -> 1950300 | H15: =H14*ASSUMPTIONS!$B$35 -> 2093405.6 | I15: =I14*ASSUMPTIONS!$B$35 -> 2247011.8
A16: Net Earned Premium | B16: =B14-B15 -> 51652500 | C16: =C14-C15 -> 50599080 | D16: =D14-D15 -> 53357760 | E16: =E14-E15 -> 56537420 | F16: =F14-F15 -> 59771400 | G16: =G14-G15 -> 63059700 | H16: =H14-H15 -> 67686782 | I16: =I14-I15 -> 72653382
A18: DISABILITY
A19: Policies in Force | B19: 98000 | C19: 91000 | D19: 96000 | E19: 103000 | F19: 109000 | G19: 115000 | H19: =G19*(1+ASSUMPTIONS!$B$28) -> 118903.82 | I19: =H19*(1+ASSUMPTIONS!$B$28) -> 122940.17
A20: Avg Premium | B20: 512 | C20: 515 | D20: 518 | E20: 522 | F20: 526 | G20: 531 | H20: =G20*(1+ASSUMPTIONS!$B$30) -> 552.87005 | I20: =H20*(1+ASSUMPTIONS!$B$30) -> 575.64084
A21: Gross Written Premium | B21: =B20*B19 -> 50176000 | C21: =C20*C19 -> 46865000 | D21: =D20*D19 -> 49728000 | E21: =E20*E19 -> 53766000 | F21: =F20*F19 -> 57334000 | G21: =G20*G19 -> 61065000 | H21: =H20*H19 -> 65738362 | I21: =I20*I19 -> 70769381
A22: Reinsurance Ceded | B22: =B21*ASSUMPTIONS!$B$35 -> 1505280 | C22: =C21*ASSUMPTIONS!$B$35 -> 1405950 | D22: =D21*ASSUMPTIONS!$B$35 -> 1491840 | E22: =E21*ASSUMPTIONS!$B$35 -> 1612980 | F22: =F21*ASSUMPTIONS!$B$35 -> 1720020 | G22: =G21*ASSUMPTIONS!$B$35 -> 1831950 | H22: =H21*ASSUMPTIONS!$B$35 -> 1972150.9 | I22: =I21*ASSUMPTIONS!$B$35 -> 2123081.4
A23: Net Earned Premium | B23: =B21-B22 -> 48670720 | C23: =C21-C22 -> 45459050 | D23: =D21-D22 -> 48236160 | E23: =E21-E22 -> 52153020 | F23: =F21-F22 -> 55613980 | G23: =G21-G22 -> 59233050 | H23: =H21-H22 -> 63766211 | I23: =I21-I22 -> 68646300
A25: TOTAL COMPANY
A26: Total Policies in Force | B26: =SUM(B5,B12,B19) -> 425000 | C26: =SUM(C5,C12,C19) -> 401000 | D26: =SUM(D5,D12,D19) -> 418000 | E26: =SUM(E5,E12,E19) -> 442000 | F26: =SUM(F5,F12,F19) -> 463000 | G26: =SUM(G5,G12,G19) -> 484000 | H26: =SUM(H5,H12,H19) -> 497254.86 | I26: =SUM(I5,I12,I19) -> 510888.49
A27: Total GWP | B27: =SUM(B7,B14,B21) -> 185751000 | C27: =SUM(C7,C14,C21) -> 176085000 | D27: =SUM(D7,D14,D21) -> 185192000 | E27: =SUM(E7,E14,E21) -> 198156000 | F27: =SUM(F7,F14,F21) -> 209702000 | G27: =SUM(G7,G14,G21) -> 221547000 | H27: =SUM(H7,H14,H21) -> 2.3602634e+08 | I27: =SUM(I7,I14,I21) -> 2.5147898e+08
A28: Total Reinsurance Ceded | B28: =SUM(B8,B15,B22) -> 5572530 | C28: =SUM(C8,C15,C22) -> 5282550 | D28: =SUM(D8,D15,D22) -> 5555760 | E28: =SUM(E8,E15,E22) -> 5944680 | F28: =SUM(F8,F15,F22) -> 6291060 | G28: =SUM(G8,G15,G22) -> 6646410 | H28: =SUM(H8,H15,H22) -> 7080790.2 | I28: =SUM(I8,I15,I22) -> 7544369.3
A29: Total Net Earned Premium | B29: =SUM(B9,B16,B23) -> 180178470 | C29: =SUM(C9,C16,C23) -> 170802450 | D29: =SUM(D9,D16,D23) -> 179636240 | E29: =SUM(E9,E16,E23) -> 192211320 | F29: =SUM(F9,F16,F23) -> 203410940 | G29: =SUM(G9,G16,G23) -> 214900590 | H29: =SUM(H9,H16,H23) -> 2.2894555e+08 | I29: =SUM(I9,I16,I23) -> 2.4393461e+08
A30: GWP Growth % | B30: - | C30: =((C27-B27)/B27) -> -0.052037405 | D30: =((D27-C27)/C27) -> 0.05171934 | E30: =((E27-D27)/D27) -> 0.070003024 | F30: =((F27-E27)/E27) -> 0.058267224 | G30: =((G27-F27)/F27) -> 0.056484917 | H30: =((H27-G27)/G27) -> 0.06535562 | I30: =((I27-H27)/H27) -> 0.065469964

Sheet P&L
A1: COMBINED INSURANCE (CHUBB) — UNDERWRITING P&L 2019-2026
B3: 2019 A | C3: 2020 A | D3: 2021 A | E3: 2022 A | F3: 2023 A | G3: 2024 A | H3: 2025 F | I3: 2026 F
A4: REVENUE
A5: A&H Net Earned Premium | B5: =REVENUE!B9 -> 79855250 | C5: =REVENUE!C9 -> 74744320 | D5: =REVENUE!D9 -> 78042320 | E5: =REVENUE!E9 -> 83520880 | F5: =REVENUE!F9 -> 88025560 | G5: =REVENUE!G9 -> 92607840 | H5: =REVENUE!H9 -> 97492558 | I5: =REVENUE!I9 -> 1.0263493e+08
A6: Life Net Earned Premium | B6: =REVENUE!B16 -> 51652500 | C6: =REVENUE!C16 -> 50599080 | D6: =REVENUE!D16 -> 53357760 | E6: =REVENUE!E16 -> 56537420 | F6: =REVENUE!F16 -> 59771400 | G6: =REVENUE!G16 -> 63059700 | H6: =REVENUE!H16 -> 67686782 | I6: =REVENUE!I16 -> 72653382
A7: Disability Net Earned Premium | B7: =REVENUE!B23 -> 48670720 | C7: =REVENUE!C23 -> 45459050 | D7: =REVENUE!D23 -> 48236160 | E7: =REVENUE!E23 -> 52153020 | F7: =REVENUE!F23 -> 55613980 | G7: =REVENUE!G23 -> 59233050 | H7: =REVENUE!H23 -> 63766211 | I7: =REVENUE!I23 -> 68646300
A8: Total Net Earned Premium | B8: =B5+B6+B7 -> 180178470 | C8: =C5+C6+C7 -> 170802450 | D8: =D5+D6+D7 -> 179636240 | E8: =E5+E6+E7 -> 192211320 | F8: =F5+F6+F7 -> 203410940 | G8: =G5+G6+G7 -> 214900590 | H8: =H5+H6+H7 -> 2.2894555e+08 | I8: =I5+I6+I7 -> 2.4393461e+08
A9: NEP Growth % | B9: - | C9: =((C8-B8)/B8) -> -0.052037405 | D9: =((D8-C8)/C8) -> 0.05171934 | E9: =((E8-D8)/D8) -> 0.070003024 | F9: =((F8-E8)/E8) -> 0.058267224 | G9: =((G8-F8)/F8) -> 0.056484917 | H9: =((H8-G8)/G8) -> 0.06535562 | I9: =((I8-H8)/H8) -> 0.065469964
A11: CLAIMS
A12: A&H Claims | B12: =ACTUALS!F4 -> 44455500 | C12: =ACTUALS!F5 -> 44292160 | D12: =ACTUALS!F6 -> 43446240 | E12: =ACTUALS!F7 -> 45634120 | F12: =ACTUALS!F8 -> 47188960 | G12: =ACTUALS!F9 -> 48244800 | H12: =G12*(1+ASSUMPTIONS!$B$32) -> 49055622 | I12: =H12*(1+ASSUMPTIONS!$B$32) -> 49880071
A13: Life Claims | B13: =ACTUALS!F10 -> 22365000 | C13: =ACTUALS!F11 -> 23474000 | D13: =ACTUALS!F12 -> 23695190 | E13: =ACTUALS!F13 -> 24480120 | F13: =ACTUALS!F14 -> 25280200 | G13: =ACTUALS!F15 -> 26136000 | H13: =G13*(1+ASSUMPTIONS!$B$33) -> 26965404 | I13: =H13*(1+ASSUMPTIONS!$B$33) -> 27821128
A14: Disability Claims | B14: =ACTUALS!F16 -> 28599320 | C14: =ACTUALS!F17 -> 28591650 | D14: =ACTUALS!F18 -> 27849680 | E14: =ACTUALS!F19 -> 28479980 | F14: =ACTUALS!F20 -> 29203340 | G14: =ACTUALS!F21 -> 30088500 | H14: =G14*(1+ASSUMPTIONS!$B$34) -> 30402158 | I14: =H14*(1+ASSUMPTIONS!$B$34) -> 30719086
A15: Total Claims | B15: =B12+B13+B14 -> 95419820 | C15: =C12+C13+C14 -> 96357810 | D15: =D12+D13+D14 -> 94991110 | E15: =E12+E13+E14 -> 98594220 | F15: =F12+F13+F14 -> 101672500 | G15: =G12+G13+G14 -> 104469300 | H15: =H12+H13+H14 -> 1.0642318e+08 | I15: =I12+I13+I14 -> 1.0842028e+08
A17: OPERATING EXPENSES
A18: A&H Operating Expenses | B18: =ACTUALS!H4 -> 30504706 | C18: =ACTUALS!H5 -> 29972472 | D18: =ACTUALS!H6 -> 29499997 | E18: =ACTUALS!H7 -> 30819205 | F18: =ACTUALS!H8 -> 31865253 | G18: =ACTUALS!H9 -> 33153607 | H18: =G18*(1+ASSUMPTIONS!$B$36) -> 33076648 | I18: =H18*(1+ASSUMPTIONS!$B$36) -> 32999867
A19: Life Operating Expenses | B19: =ACTUALS!H10 -> 20557695 | C19: =ACTUALS!H11 -> 20846821 | D19: =ACTUALS!H12 -> 21129673 | E19: =ACTUALS!H13 -> 21936519 | F19: =ACTUALS!H14 -> 22772903 | G19: =ACTUALS!H15 -> 23710447 | H19: =G19*(1+ASSUMPTIONS!$B$37) -> 25191064 | I19: =H19*(1+ASSUMPTIONS!$B$37) -> 26764140
A20: Disability Operating Expenses | B20: =ACTUALS!H16 -> 19176264 | C20: =ACTUALS!H17 -> 19001883 | D20: =ACTUALS!H18 -> 18908575 | E20: =ACTUALS!H19 -> 19765995 | F20: =ACTUALS!H20 -> 20632787 | G20: =ACTUALS!H21 -> 21797762 | H20: =G20*(1+ASSUMPTIONS!$B$38) -> 21677570 | I20: =H20*(1+ASSUMPTIONS!$B$38) -> 21558040
A21: Total Operating Expenses | B21: =SUM(B18:B20) -> 70238664 | C21: =SUM(C18:C20) -> 69821176 | D21: =SUM(D18:D20) -> 69538245 | E21: =SUM(E18:E20) -> 72521718 | F21: =SUM(F18:F20) -> 75270943 | G21: =SUM(G18:G20) -> 78661816 | H21: =SUM(H18:H20) -> 79945282 | I21: =SUM(I18:I20) -> 81322047
A23: UNDERWRITING INCOME
A24: A&H Underwriting Income | B24: =B5-B12-B18 -> 4895044.5 | C24: =C5-C12-C18 -> 479687.68 | D24: =D5-D12-D18 -> 5096083 | E24: =E5-E12-E18 -> 7067555.3 | F24: =F5-F12-F18 -> 8971347.3 | G24: =G5-G12-G18 -> 11209433 | H24: =H5-H12-H18 -> 15360288 | I24: =I5-I12-I18 -> 19754988
A25: Life Underwriting Income | B25: =B6-B13-B19 -> 8729805 | C25: =C6-C13-C19 -> 6278259 | D25: =D6-D13-D19 -> 8532897 | E25: =E6-E13-E19 -> 10120781 | F25: =F6-F13-F19 -> 11718297 | G25: =G6-G13-G19 -> 13213253 | H25: =H6-H13-H19 -> 15530314 | I25: =I6-I13-I19 -> 18068115
A26: Disability Underwriting Income | B26: =B7-B14-B20 -> 895136.32 | C26: =C7-C14-C20 -> -2134482.9 | D26: =D7-D14-D20 -> 1477905.3 | E26: =E7-E14-E20 -> 3907045.4 | F26: =F7-F14-F20 -> 5777853.4 | G26: =G7-G14-G20 -> 7346787.6 | H26: =H7-H14-H20 -> 11686483 | I26: =I7-I14-I20 -> 16369174
A27: Total Underwriting Income | B27: =SUM(B24:B26) -> 14519986 | C27: =SUM(C24:C26) -> 4623463.8 | D27: =SUM(D24:D26) -> 15106885 | E27: =SUM(E24:E26) -> 21095382 | F27: =SUM(F24:F26) -> 26467497 | G27: =SUM(G24:G26) -> 31769474 | H27: =SUM(H24:H26) -> 42577086 | I27: =SUM(I24:I26) -> 54192277
A29: KEY METRICS
A30: Loss Ratio
A31: Loss Ratio — A&H | B31: =B12/B5 -> 0.55670103 | C31: =C12/C5 -> 0.59258229 | D31: =D12/D5 -> 0.55670103 | E31: =E12/E5 -> 0.54637978 | F31: =F12/F5 -> 0.53608247 | G31: =G12/G5 -> 0.52095805 | H31: =H12/H5 -> 0.50317299 | I31: =I12/I5 -> 0.4859951
A32: Loss Ratio — Life | B32: =B13/B6 -> 0.43298969 | C32: =B15/B8 -> 0.52958503 | D32: =D13/D6 -> 0.44408142 | E32: =E13/E6 -> 0.43298969 | F32: =F13/F6 -> 0.4229481 | G32: =G13/G6 -> 0.41446439 | H32: =H13/H6 -> 0.39838507 | I32: =I13/I6 -> 0.38292956
A33: Loss Ratio — Disability | B33: =B14/B7 -> 0.58760832 | C33: =C14/C7 -> 0.62895397 | D33: =D14/D7 -> 0.57736105 | E33: =E14/E7 -> 0.54608496 | F33: =F14/F7 -> 0.5251079 | G33: =G14/G7 -> 0.5079681 | H33: =H14/H7 -> 0.47677535 | I33: =I14/I7 -> 0.44749806
A34: Blended Loss Ratio | B34: =B15/B8 -> 0.52958503 | C34: =C15/C8 -> 0.5641477 | D34: =D15/D8 -> 0.52879703 | E34: =E15/E8 -> 0.512947 | F34: =F15/F8 -> 0.49983791 | G34: =G15/G8 -> 0.48612849 | H34: =H15/H8 -> 0.46484058 | I34: =I15/I8 -> 0.44446454
A35: Expense Ratio
A36: Expense Ratio — A&H | B36: =B18/B5 -> 0.382 | C36: =C18/C5 -> 0.401 | D36: =D18/D5 -> 0.378 | E36: =E18/E5 -> 0.369 | F36: =F18/F5 -> 0.362 | G36: =G18/G5 -> 0.358 | H36: =H18/H5 -> 0.33927356 | I36: =I18/I5 -> 0.32152668
A37: Expense Ratio — Life | B37: =B19/B6 -> 0.398 | C37: =C19/C6 -> 0.412 | D37: =D19/D6 -> 0.396 | E37: =E19/E6 -> 0.388 | F37: =F19/F6 -> 0.381 | G37: =G19/G6 -> 0.376 | H37: =H19/H6 -> 0.3721711 | I37: =I19/I6 -> 0.36838119
A38: Expense Ratio — Disability | B38: =B20/B7 -> 0.394 | C38: =C20/C7 -> 0.418 | D38: =D20/D7 -> 0.392 | E38: =E20/E7 -> 0.379 | F38: =F20/F7 -> 0.371 | G38: =G20/G7 -> 0.368 | H38: =H20/H7 -> 0.33995386 | I38: =I20/I7 -> 0.31404519
A39: Blended Expense Ratio | B39: =B21/B8 -> 0.38982829 | C39: =C21/C8 -> 0.40878322 | D39: =D21/D8 -> 0.38710588 | E39: =E21/E8 -> 0.37730201 | F39: =F21/F8 -> 0.37004373 | G39: =G21/G8 -> 0.36603816 | H39: =H21/H8 -> 0.34918906 | I39: =I21/I8 -> 0.33337642
A40: Combined Ratio
A41: Combined Ratio — A&H | B41: =SUM(B31,B36) -> 0.93870103 | C41: =SUM(C31,C36) -> 0.99358229 | D41: =SUM(D31,D36) -> 0.93470103 | E41: =SUM(E31,E36) -> 0.91537978 | F41: =SUM(F31,F36) -> 0.89808247 | G41: =SUM(G31,G36) -> 0.87895805 | H41: =SUM(H31,H36) -> 0.84244655 | I41: =SUM(I31,I36) -> 0.80752178
A42: Combined Ratio — Life | B42: =SUM(B32,B37) -> 0.83098969 | C42: =SUM(C32,C37) -> 0.94158503 | D42: =SUM(D32,D37) -> 0.84008142 | E42: =SUM(E32,E37) -> 0.82098969 | F42: =SUM(F32,F37) -> 0.8039481 | G42: =SUM(G32,G37) -> 0.79046439 | H42: =SUM(H32,H37) -> 0.77055617 | I42: =SUM(I32,I37) -> 0.75131075
A43: Combined Ratio — Disability | B43: =SUM(B33,B38) -> 0.98160832 | C43: =SUM(C33,C38) -> 1.046954 | D43: =SUM(D33,D38) -> 0.96936105 | E43: =SUM(E33,E38) -> 0.92508496 | F43: =SUM(F33,F38) -> 0.8961079 | G43: =SUM(G33,G38) -> 0.8759681 | H43: =SUM(H33,H38) -> 0.81672922 | I43: =SUM(I33,I38) -> 0.76154325
A44: Blended Combined Ratio | B44: =C34+C39 -> 0.97293093 | C44: =D34+D39 -> 0.91590291 | D44: =E34+E39 -> 0.89024901 | E44: =F34+F39 -> 0.86988164 | F44: =G34+G39 -> 0.85216665 | G44: =H34+H39 -> 0.81402964 | H44: =I34+I39 -> 0.77784096 | I44: =J34+J39 -> 0
A45: Underwriting Margin % | B45: =B27/B8 -> 0.080586686 | C45: =C27/C8 -> 0.027069072 | D45: =D27/D8 -> 0.084097092 | E45: =E27/E8 -> 0.10975099 | F45: =F27/F8 -> 0.13011836 | G45: =G27/G8 -> 0.14783335 | H45: =H27/H8 -> 0.18597036 | I45: =I27/I8 -> 0.22215904

Sheet INSIGHT
A1: COMBINED INSURANCE (CHUBB) — EXECUTIVE INSIGHT & MANAGEMENT REPORT
A3: EXECUTIVE SUMMARY
A4: Combined Insurance Company of America (a Chubb subsidiary) has delivered consistent and improving underwriting performance from 2019 to 2024 — growing Gross Written Premium from $185.8M to $221.5M, a 19.3% increase over six years, while simultaneously improving the blended combined ratio from 91.9% in 2019 to 85.2% in 2024, a 670 basis point improvement. Underwriting income more than doubled from $14.5M to $31.8M over the same period. The 2025 and 2026 forecast projects continued premium growth to $236.0M and $251.5M respectively under the Base scenario, with the combined ratio improving further to 83.5% and 81.8% — driven by disciplined claims management and operational efficiency gains across all three product lines.
A16: REVENUE STORY — 2019 TO 2026
A17: Gross Written Premium grew from $185.8M in 2019 to $221.5M in 2024 — a compound annual growth rate of approximately 3.6%. Growth was driven by two levers working simultaneously — policy count expansion and annual premium rate increases. Total policies in force grew from 425,000 in 2019 to 484,000 in 2024, a 13.9% increase, while the blended average premium increased from $437 to $458 per policy annually. The only revenue contraction occurred in 2020 — GWP fell 5.2% to $176.1M as COVID-19 disrupted Combined's direct sales force model, reducing new policy sales across all three product lines. Recovery was swift — 2021 delivered 5.2% GWP growth as agents returned to the field and new policy sales normalized. From 2022 onwards GWP has grown consistently at 5.6-7.0% annually. The 2025 and 2026 forecast projects continued GWP growth of 6.5% annually, driven by Base policy growth assumptions of 2.08% for A&H, 3.09% for Life, and 3.39% for Disability, combined with premium rate increases of 3.13%, 4.12%, and 4.15% respectively.
A32: CLAIMS & LOSS RATIO ANALYSIS
A34: Total claims paid grew from $95.4M in 2019 to $104.5M in 2024 — a 9.5% increase over six years, significantly slower than premium growth of 19.3%. This divergence is the primary driver of combined ratio improvement. The blended loss ratio declined from 53.0% in 2019 to 48.6% in 2024 — a 440 basis point improvement reflecting better underwriting discipline, improved risk selection, and favorable claims experience across all three product lines. COVID-19 caused a temporary loss ratio spike in 2020 — the blended loss ratio increased to 56.4% as Accident & Health claims rose sharply and Disability claims remained elevated as workers filed income replacement claims during lockdowns. Disability specifically generated a negative underwriting income of -$2.1M in 2020 — the only product line to record an underwriting loss in the entire historical period. This is a critical risk to monitor — Disability is the most economically sensitive product line and would be the first to deteriorate in a Bear scenario. The 2025 Base forecast assumes the loss ratio improvement trend continues — blended loss ratio declining to 47.3% in 2025 and 46.0% in 2026 driven by continued improvements in claims adjudication, policyholder quality, and risk management protocols.
A53: EXPENSE RATIO & OPERATIONAL EFFICIENCY
A55: The blended expense ratio declined from 39.0% in 2019 to 36.6% in 2024 — a 240 basis point improvement reflecting operational leverage as premium volume grows faster than fixed administrative costs. The largest expense driver is agent commissions — Combined Insurance operates a large direct sales force model where agents receive commission on every policy sold and renewed. As the agent force becomes more productive and premium per agent increases, the expense ratio benefits from scale. Technology investment in policy administration and claims processing has also contributed to efficiency gains. Life insurance carries the highest expense ratio at 37.6% in 2024 — reflecting higher commission rates paid to agents for more complex life products. A&H at 35.8% and Disability at 36.8% are more efficient product lines. The 2025 and 2026 forecast assumes continued expense ratio improvement toward 35.2% and 34.8% blended respectively — supported by technology automation of back-office processes and increasing agent productivity.
A69: PRODUCT LINE HIGHLIGHTS
A71: Accident & Health is the largest and most profitable product line — generating $92.6M in Net Earned Premium in 2024 (43% of total) with a combined ratio of 87.9%. A&H benefits from high policy volume (204,000 policies) and relatively predictable claims frequency, making it the most stable earnings contributor. Life insurance at $63.1M Net Earned Premium (29% of total) is the most profitable product line with a combined ratio of 79.1% in 2024 — the lowest combined ratio in the portfolio. Life policies generate lower claims frequency and the death benefit nature of the product creates long-duration premium streams with predictable actuarial experience. Disability at $59.2M Net Earned Premium (28% of total) carries the highest combined ratio at 87.6% in 2024 and is the most economically sensitive product line. Disability claims are directly correlated with employment conditions — economic downturns drive higher disability claim rates as workers experiencing job stress or layoffs file income replacement claims. This is Combined's primary underwriting risk.
A87: SCENARIO ANALYSIS — RISKS AND OPPORTUNITIES
... A149: 6. Build reinsurance optimization review — Reinsurance cost is fixed at 3% of GWP. As the book grows to $236M-$251M in 2025-2026, the absolute cost of reinsurance increases from $6.6M to $7.5M annually. A periodic review of reinsurance structure and counterparty terms could identify opportunities to reduce the reinsurance rate while maintaining catastrophic loss protection.
