Workbook

Sheet Data
A1: Month | B1: Deliveries | C1: Subtotal | D1: Delivery Fees | E1: Commission | F1: Dasher Costs | H1: Cohort | I1: Customers Acquired
A2: 45108 | B2: 914395 | C2: 30322972 | D2: 3262196.3 | E2: 5588748.7 | F2: 5863681.3 | H2: 45474 | I2: 10000
A3: 45139 | B3: 948388 | C3: 31496114 | D3: 3334817 | E3: 5807174.5 | F3: 6165788.7 | H3: 45505 | I3: =I2+1000 -> 11000
A4: 45170 | B4: 956516 | C4: 31921908 | D4: 3342796.5 | E4: 5859473.3 | F4: 6389738.9 | H4: 45536 | I4: =I3+1000 -> 12000
A5: 45200 | B5: 1017972 | C5: 34257435 | D5: 3617001.9 | E5: 6246094.9 | F5: 6777574.2 | H5: 45566 | I5: =I4+1000 -> 13000
A6: 45231 | B6: 922301 | C6: 30795749 | D6: 3267176.4 | E6: 5628007.7 | F6: 6044249 | H6: 45597 | I6: =I5+1000 -> 14000
A7: 45261 | B7: 952400 | C7: 32565192 | D7: 3349130.1 | E7: 5911230.1 | F7: 6136147.2 | H7: 45627 | I7: =I6+1000 -> 15000
A8: 45292 | B8: 980540 | C8: 33575299 | D8: 3434231.6 | E8: 6062256.2 | F8: 6374449.2 | H8: 45658 | I8: =I7+1000 -> 16000
A9: 45323 | B9: 958610 | C9: 32749920 | D9: 3349378.4 | E9: 5893987.1 | F9: 6301878.9 | H9: 45689 | I9: =I8+1000 -> 17000
A10: 45352 | B10: 1047711 | C10: 35740386 | D10: 3734474 | E10: 6406558.1 | F10: 6723076.5 | H10: 45717 | I10: =I9+1000 -> 18000
A11: 45383 | B11: 979037 | C11: 33189120 | D11: 3484622 | E11: 5923500.2 | F11: 6550510.1 | H11: 45748 | I11: =I10+1000 -> 19000
A12: 45413 | B12: 1028592 | C12: 34904386 | D12: 3612014.4 | E12: 6231104.6 | F12: 6905654.5 | H12: 45778 | I12: =I11+1000 -> 20000
A13: 45444 | B13: 990651 | C13: 33777694 | D13: 3512049.4 | E13: 5967598.8 | F13: 6498368 | H13: 45809 | I13: =I12+1000 -> 21000
A15: Fees/Delivery | B15: Commission/Delivery | C15: Dasher Cost/Delivery | D15: Subtotal/Delivery | E15: Commission Rate | F15: Month
A16: =D2/B2 -> 3.5676007 | B16: =E2/B2 -> 6.1119633 | C16: =F2/B2 -> 6.4126349 | D16: =C2/B2 -> 33.161787 | E16: =E2/C2 -> 0.18430742 | F16: Jul
A17: =D3/B3 -> 3.5163003 | B17: =E3/B3 -> 6.1232053 | C17: =F3/B3 -> 6.5013356 | D17: =C3/B3 -> 33.210156 | E17: =E3/C3 -> 0.18437749 | F17: Aug
A18: =D4/B4 -> 3.4947628 | B18: =E4/B4 -> 6.1258498 | C18: =F4/B4 -> 6.6802217 | D18: =C4/B4 -> 33.373105 | E18: =E4/C4 -> 0.18355649 | F18: Sep
A19: =D5/B5 -> 3.5531448 | B19: =E5/B5 -> 6.1358219 | C19: =F5/B5 -> 6.6579181 | D19: =C5/B5 -> 33.65263 | E19: =E5/C5 -> 0.18232816 | F19: Oct
A20: =D6/B6 -> 3.5424188 | B20: =E6/B6 -> 6.1021377 | C20: =F6/B6 -> 6.5534451 | D20: =C6/B6 -> 33.390129 | E20: =E6/C6 -> 0.18275274 | F20: Nov
A21: =D7/B7 -> 3.5165162 | B21: =E7/B7 -> 6.2066675 | C21: =F7/B7 -> 6.4428257 | D21: =C7/B7 -> 34.192768 | E21: =E7/C7 -> 0.18151989 | F21: Dec
A22: =D8/B8 -> 3.5023881 | B22: =E8/B8 -> 6.182569 | C22: =F8/B8 -> 6.5009578 | D22: =C8/B8 -> 34.241641 | E22: =E8/C8 -> 0.18055703 | F22: Jan
A23: =D9/B9 -> 3.4939949 | B23: =E9/B9 -> 6.1484724 | C23: =F9/B9 -> 6.5739757 | D23: =C9/B9 -> 34.163967 | E23: =E9/C9 -> 0.17996951 | F23: Feb
A24: =D10/B10 -> 3.5644123 | B24: =E10/B10 -> 6.1148142 | C24: =F10/B10 -> 6.4169189 | D24: =C10/B10 -> 34.112829 | E24: =E10/C10 -> 0.17925263 | F24: Mar
A25: =D11/B11 -> 3.5592342 | B25: =E11/B11 -> 6.0503333 | C25: =F11/B11 -> 6.6907687 | D25: =C11/B11 -> 33.899761 | E25: =E11/C11 -> 0.17847717 | F25: Apr
A26: =D12/B12 -> 3.5116104 | B26: =E12/B12 -> 6.0578972 | C26: =F12/B12 -> 6.7136965 | D26: =C12/B12 -> 33.934141 | E26: =E12/C12 -> 0.17851925 | F26: May
A27: =D13/B13 -> 3.5451934 | B27: =E13/B13 -> 6.0239164 | C27: =F13/B13 -> 6.5596946 | D27: =C13/B13 -> 34.096462 | E27: =E13/C13 -> 0.17667277 | F27: Jun
A28: AVERAGE | B28: AVERAGE | C28: AVERAGE | D28: AVERAGE | E28: AVERAGE | F28: Churn
A29: =AVERAGE(A16:A27) -> 3.5306314 | B29: =AVERAGE(B16:B27) -> 6.115304 | C29: =AVERAGE(C16:C27) -> 6.5586995 | D29: =AVERAGE(D16:D27) -> 33.785781 | E29: =AVERAGE(E16:E27) -> 0.18102421

Sheet ASSUMPTIONS
A1: Data sourced from company Activities
A2: Driver | B2: Value | D2: Toggle
A3: Avg Order request / Month | B3: =IF($D$3="Base Case",SCENERIO!C8,IF($D$3="Worst Case",SCENERIO!B8,SCENERIO!D8)) -> 2.5 | D3: Best Case
A4: Customer Acqusition Cost | B4: =IF($D$3="Base Case",SCENERIO!C9,IF($D$3="Worst Case",SCENERIO!B9,SCENERIO!D9)) -> 10
A5: 1st two months | B5: 0.3
A6: 3rd Month | B6: 0.2
A7: 4th month | B7: =IF($D$3="Base Case",SCENERIO!C6,IF($D$3="Worst Case",SCENERIO!B6,SCENERIO!D6)) -> 0.08
A8: Churn April 2025 - Jun 2025 | B8: =IF($D$3="Base Case",SCENERIO!C7,IF($D$3="Worst Case",SCENERIO!B7,SCENERIO!D7)) -> 0.03
A9: Delivery /Order post Apr 2025 | B9: =1 -> 1
A10: Monthly customer growth | B10: =1000 -> 1000
A11: Avg fee per delivery | B11: =IF($D$3="Base Case",SCENERIO!C10,IF($D$3="Worst Case",SCENERIO!B10,SCENERIO!D10)) -> 4
A12: Avg Commission per delivery | B12: =Data!B29 -> 6.115304
A13: Avg commission rate | B13: =Data!E29 -> 0.18102421
A14: Avg Subtotal per order | B14: =Data!D29 -> 33.785781
A15: Dasher cost per delivery | B15: =Data!C29 -> 6.5586995

Sheet P&L
A1: Customer Data
B2: 45474 | C2: 45505 | D2: 45536 | E2: 45566 | F2: 45597 | G2: 45627 | H2: 45658 | I2: 45689 | J2: 45717 | K2: 45748 | L2: 45778 | M2: 45809
A3: Beginnig Customer | B3: =10000 -> 10000 | C3: =B3+ASSUMPTIONS!$B$10 -> 11000 | D3: =C3+ASSUMPTIONS!$B$10 -> 12000 | E3: =D3+ASSUMPTIONS!$B$10 -> 13000 | F3: =E3+ASSUMPTIONS!$B$10 -> 14000 | G3: =F3+ASSUMPTIONS!$B$10 -> 15000 | H3: =G3+ASSUMPTIONS!$B$10 -> 16000 | I3: =H3+ASSUMPTIONS!$B$10 -> 17000 | J3: =I3+ASSUMPTIONS!$B$10 -> 18000 | ... M3: =L3+ASSUMPTIONS!$B$10 -> 21000
A4: =Data!F16&" "&Data!$F$28 -> Jul Churn | B4: =B3*(1-ASSUMPTIONS!$B$5) -> 7000 | C4: =B4*(1-ASSUMPTIONS!$B$5) -> 4900 | D4: =C4*(1-ASSUMPTIONS!$B$6) -> 3920 | E4: =D4*(1-ASSUMPTIONS!$B$7) -> 3606.4 | F4: =E4*(1-ASSUMPTIONS!$B$7) -> 3317.888 | G4: =F4*(1-ASSUMPTIONS!$B$7) -> 3052.457 | H4: =G4*(1-ASSUMPTIONS!$B$7) -> 2808.2604 | I4: =H4*(1-ASSUMPTIONS!$B$7) -> 2583.5996 | J4: =I4*(1-ASSUMPTIONS!$B$7) -> 2376.9116 | K4: =(J4*(1-(ASSUMPTIONS!$B$7+ASSUMPTIONS!$B$8))) -> 2115.4513 | L4: =(K4*(1-(ASSUMPTIONS!$B$7+ASSUMPTIONS!$B$8))) -> 1882.7517 | M4: =(L4*(1-(ASSUMPTIONS!$B$7+ASSUMPTIONS!$B$8))) -> 1675.649
A5: =Data!F17&" "&Data!$F$28 -> Aug Churn | C5: =C3*(1-ASSUMPTIONS!$B$5) -> 7700 | D5: =C5*(1-ASSUMPTIONS!$B$5) -> 5390 | E5: =D5*(1-ASSUMPTIONS!$B$6) -> 4312 | F5: =E5*(1-ASSUMPTIONS!$B$7) -> 3967.04 | G5: =F5*(1-ASSUMPTIONS!$B$7) -> 3649.6768 | H5: =G5*(1-ASSUMPTIONS!$B$7) -> 3357.7027 | I5: =H5*(1-ASSUMPTIONS!$B$7) -> 3089.0864 | J5: =I5*(1-ASSUMPTIONS!$B$7) -> 2841.9595 | K5: =(J5*(1-(ASSUMPTIONS!$B$7+ASSUMPTIONS!$B$8))) -> 2529.344 | L5: =(K5*(1-(ASSUMPTIONS!$B$7+ASSUMPTIONS!$B$8))) -> 2251.1161 | M5: =(L5*(1-(ASSUMPTIONS!$B$7+ASSUMPTIONS!$B$8))) -> 2003.4934
A6: =Data!F18&" "&Data!$F$28 -> Sep Churn | D6: =D3*(1-ASSUMPTIONS!$B$5) -> 8400 | E6: =D6*(1-ASSUMPTIONS!$B$5) -> 5880 | F6: =E6*(1-ASSUMPTIONS!$B$6) -> 4704 | G6: =F6*(1-ASSUMPTIONS!$B$7) -> 4327.68 | H6: =G6*(1-ASSUMPTIONS!$B$7) -> 3981.4656 | I6: =H6*(1-ASSUMPTIONS!$B$7) -> 3662.9484 | J6: =I6*(1-ASSUMPTIONS!$B$7) -> 3369.9125 | K6: =(J6*(1-(ASSUMPTIONS!$B$7+ASSUMPTIONS!$B$8))) -> 2999.2221 | L6: =(K6*(1-(ASSUMPTIONS!$B$7+ASSUMPTIONS!$B$8))) -> 2669.3077 | M6: =(L6*(1-(ASSUMPTIONS!$B$7+ASSUMPTIONS!$B$8))) -> 2375.6838
A7: =Data!F19&" "&Data!$F$28 -> Oct Churn | E7: =E3*(1-ASSUMPTIONS!$B$5) -> 9100 | F7: =E7*(1-ASSUMPTIONS!$B$5) -> 6370 | G7: =F7*(1-ASSUMPTIONS!$B$6) -> 5096 | H7: =G7*(1-ASSUMPTIONS!$B$7) -> 4688.32 | I7: =H7*(1-ASSUMPTIONS!$B$7) -> 4313.2544 | J7: =I7*(1-ASSUMPTIONS!$B$7) -> 3968.194 | K7: =(J7*(1-(ASSUMPTIONS!$B$7+ASSUMPTIONS!$B$8))) -> 3531.6927 | L7: =(K7*(1-(ASSUMPTIONS!$B$7+ASSUMPTIONS!$B$8))) -> 3143.2065 | M7: =(L7*(1-(ASSUMPTIONS!$B$7+ASSUMPTIONS!$B$8))) -> 2797.4538
A8: =Data!F20&" "&Data!$F$28 -> Nov Churn | F8: =F3*(1-ASSUMPTIONS!$B$5) -> 9800 | G8: =F8*(1-ASSUMPTIONS!$B$5) -> 6860 | H8: =G8*(1-ASSUMPTIONS!$B$6) -> 5488 | I8: =H8*(1-ASSUMPTIONS!$B$7) -> 5048.96 | J8: =I8*(1-ASSUMPTIONS!$B$7) -> 4645.0432 | K8: =(J8*(1-(ASSUMPTIONS!$B$7+ASSUMPTIONS!$B$8))) -> 4134.0884 | L8: =(K8*(1-(ASSUMPTIONS!$B$7+ASSUMPTIONS!$B$8))) -> 3679.3387 | M8: =(L8*(1-(ASSUMPTIONS!$B$7+ASSUMPTIONS!$B$8))) -> 3274.6115
A9: =Data!F21&" "&Data!$F$28 -> Dec Churn | G9: =G3*(1-ASSUMPTIONS!$B$5) -> 10500 | H9: =G9*(1-ASSUMPTIONS!$B$5) -> 7350 | I9: =H9*(1-ASSUMPTIONS!$B$6) -> 5880 | J9: =I9*(1-ASSUMPTIONS!$B$7) -> 5409.6 | K9: =(J9*(1-(ASSUMPTIONS!$B$7+ASSUMPTIONS!$B$8))) -> 4814.544 | L9: =(K9*(1-(ASSUMPTIONS!$B$7+ASSUMPTIONS!$B$8))) -> 4284.9442 | M9: =(L9*(1-(ASSUMPTIONS!$B$7+ASSUMPTIONS!$B$8))) -> 3813.6003
A10: =Data!F22&" "&Data!$F$28 -> Jan Churn | H10: =H3*(1-ASSUMPTIONS!$B$5) -> 11200 | I10: =H10*(1-ASSUMPTIONS!$B$5) -> 7840 | J10: =I10*(1-ASSUMPTIONS!$B$6) -> 6272 | K10: =(J10*(1-(ASSUMPTIONS!$B$7+ASSUMPTIONS!$B$8))) -> 5582.08 | L10: =(K10*(1-(ASSUMPTIONS!$B$7+ASSUMPTIONS!$B$8))) -> 4968.0512 | M10: =(L10*(1-(ASSUMPTIONS!$B$7+ASSUMPTIONS!$B$8))) -> 4421.5656
A11: =Data!F23&" "&Data!$F$28 -> Feb Churn | I11: =I3*(1-ASSUMPTIONS!$B$5) -> 11900 | J11: =I11*(1-ASSUMPTIONS!$B$5) -> 8330 | K11: =(J11*(1-(ASSUMPTIONS!$B$6+ASSUMPTIONS!$B$8))) -> 6414.1 | L11: =(K11*(1-(ASSUMPTIONS!$B$7+ASSUMPTIONS!$B$8))) -> 5708.549 | M11: =(L11*(1-(ASSUMPTIONS!$B$7+ASSUMPTIONS!$B$8))) -> 5080.6086
A12: =Data!F24&" "&Data!$F$28 -> Mar Churn | J12: =J3*(1-ASSUMPTIONS!$B$5) -> 12600 | K12: =(J12*(1-(ASSUMPTIONS!$B$5+ASSUMPTIONS!$B$8))) -> 8442 | L12: =(K12*(1-(ASSUMPTIONS!$B$6+ASSUMPTIONS!$B$8))) -> 6500.34 | M12: =(L12*(1-(ASSUMPTIONS!$B$7+ASSUMPTIONS!$B$8))) -> 5785.3026
A13: =Data!F25&" "&Data!$F$28 -> Apr Churn | K13: =(K3*(1-(ASSUMPTIONS!$B$5+ASSUMPTIONS!$B$8))) -> 12730 | L13: =(K13*(1-(ASSUMPTIONS!$B$5+ASSUMPTIONS!$B$8))) -> 8529.1 | M13: =(L13*(1-(ASSUMPTIONS!$B$6+ASSUMPTIONS!$B$8))) -> 6567.407
A14: =Data!F26&" "&Data!$F$28 -> May Churn | L14: =(L3*(1-(ASSUMPTIONS!$B$5+ASSUMPTIONS!$B$8))) -> 13400 | M14: =(L14*(1-(ASSUMPTIONS!$B$5+ASSUMPTIONS!$B$8))) -> 8978
A15: =Data!F27&" "&Data!$F$28 -> Jun Churn | M15: =(M3*(1-(ASSUMPTIONS!$B$5+ASSUMPTIONS!$B$8))) -> 14070
A16: Total Active Customers | B16: =SUM(B4:B15) -> 7000 | C16: =SUM(C4:C15) -> 12600 | D16: =SUM(D4:D15) -> 17710 | E16: =SUM(E4:E15) -> 22898.4 | F16: =SUM(F4:F15) -> 28158.928 | G16: =SUM(G4:G15) -> 33485.814 | H16: =SUM(H4:H15) -> 38873.749 | I16: =SUM(I4:I15) -> 44317.849 | ... M16: =SUM(M4:M15) -> 60843.376
A18: Orders | B18: =B16*ASSUMPTIONS!$B$3 -> 17500 | C18: =C16*ASSUMPTIONS!$B$3 -> 31500 | D18: =D16*ASSUMPTIONS!$B$3 -> 44275 | E18: =E16*ASSUMPTIONS!$B$3 -> 57246 | F18: =F16*ASSUMPTIONS!$B$3 -> 70397.32 | G18: =G16*ASSUMPTIONS!$B$3 -> 83714.534 | H18: =H16*ASSUMPTIONS!$B$3 -> 97184.372 | I18: =I16*ASSUMPTIONS!$B$3 -> 110794.62 | ... M18: =M16*ASSUMPTIONS!$B$3 -> 152108.44
A20: Revenue
A21: Delivery Fees | B21: =B18*ASSUMPTIONS!$B$11 -> 70000 | C21: =C18*ASSUMPTIONS!$B$11 -> 126000 | D21: =D18*ASSUMPTIONS!$B$11 -> 177100 | E21: =E18*ASSUMPTIONS!$B$11 -> 228984 | F21: =F18*ASSUMPTIONS!$B$11 -> 281589.28 | G21: =G18*ASSUMPTIONS!$B$11 -> 334858.14 | H21: =H18*ASSUMPTIONS!$B$11 -> 388737.49 | I21: =I18*ASSUMPTIONS!$B$11 -> 443178.49 | J21: =J18*ASSUMPTIONS!$B$11 -> 498136.21 | K21: =K18*ASSUMPTIONS!$B$9 -> 133231.31 | L21: =L18*ASSUMPTIONS!$B$9 -> 142541.76 | M21: =M18*ASSUMPTIONS!$B$9 -> 152108.44
A22: AVG Subtotal Per Order | B22: =ASSUMPTIONS!$B$14 -> 33.785781 | C22: =ASSUMPTIONS!$B$14 -> 33.785781 | D22: =ASSUMPTIONS!$B$14 -> 33.785781 | E22: =ASSUMPTIONS!$B$14 -> 33.785781 | F22: =ASSUMPTIONS!$B$14 -> 33.785781 | G22: =ASSUMPTIONS!$B$14 -> 33.785781 | H22: =ASSUMPTIONS!$B$14 -> 33.785781 | I22: =ASSUMPTIONS!$B$14 -> 33.785781 | ... M22: =ASSUMPTIONS!$B$14 -> 33.785781
A23: Commission | B23: =B18*B22*ASSUMPTIONS!$B$13 -> 107030.78 | C23: =C18*C22*ASSUMPTIONS!$B$13 -> 192655.4 | D23: =D18*D22*ASSUMPTIONS!$B$13 -> 270787.87 | E23: =E18*E22*ASSUMPTIONS!$B$13 -> 350119.08 | F23: =F18*F22*ASSUMPTIONS!$B$13 -> 430553.14 | G23: =G18*G22*ASSUMPTIONS!$B$13 -> 512001.81 | H23: =H18*H22*ASSUMPTIONS!$B$13 -> 594383.93 | I23: =I18*I22*ASSUMPTIONS!$B$13 -> 677624.83 | ... M23: =M18*M22*ASSUMPTIONS!$B$13 -> 930301.97
A24: Total Revenue | B24: =SUM(B21:B23) -> 177064.56 | C24: =SUM(C21:C23) -> 318689.18 | D24: =SUM(D21:D23) -> 447921.65 | E24: =SUM(E21:E23) -> 579136.86 | F24: =SUM(F21:F23) -> 712176.2 | G24: =SUM(G21:G23) -> 846893.73 | H24: =SUM(H21:H23) -> 983155.21 | I24: =SUM(I21:I23) -> 1120837.1 | ... M24: =SUM(M21:M23) -> 1082444.2
A26: Cost
A27: Dasher Costs | B27: =B18*ASSUMPTIONS!$B$15 -> 114777.24 | C27: =C18*ASSUMPTIONS!$B$15 -> 206599.03 | D27: =D18*ASSUMPTIONS!$B$15 -> 290386.42 | E27: =E18*ASSUMPTIONS!$B$15 -> 375459.31 | F27: =F18*ASSUMPTIONS!$B$15 -> 461714.86 | G27: =G18*ASSUMPTIONS!$B$15 -> 549058.47 | H27: =H18*ASSUMPTIONS!$B$15 -> 637403.09 | I27: =I18*ASSUMPTIONS!$B$15 -> 726668.63 | ... M27: =M18*ASSUMPTIONS!$B$15 -> 997633.53
A28: Customer Acqusition Cost | B28: =B3*ASSUMPTIONS!$B$4 -> 100000 | C28: =C3*ASSUMPTIONS!$B$4 -> 110000 | D28: =D3*ASSUMPTIONS!$B$4 -> 120000 | E28: =E3*ASSUMPTIONS!$B$4 -> 130000 | F28: =F3*ASSUMPTIONS!$B$4 -> 140000 | G28: =G3*ASSUMPTIONS!$B$4 -> 150000 | H28: =H3*ASSUMPTIONS!$B$4 -> 160000 | I28: =I3*ASSUMPTIONS!$B$4 -> 170000 | ... M28: =M3*ASSUMPTIONS!$B$4 -> 210000
A30: P&L
A31: Gross profit | B31: =B24-B27 -> 62287.323 | C31: =C24-C27 -> 112090.15 | D31: =D24-D27 -> 157535.23 | E31: =E24-E27 -> 203677.56 | F31: =F24-F27 -> 250461.34 | G31: =G24-G27 -> 297835.26 | H31: =H24-H27 -> 345752.12 | I31: =I24-I27 -> 394168.48 | ... M31: =M24-M27 -> 84810.658
A32: Net Contibuition | B32: =B31-B28 -> -37712.677 | C32: =C31-C28 -> 2090.152 | D32: =D31-D28 -> 37535.234 | E32: =E31-E28 -> 73677.555 | F32: =F31-F28 -> 110461.34 | G32: =G31-G28 -> 147835.26 | H32: =H31-H28 -> 185752.12 | I32: =I31-I28 -> 224168.48 | ... M32: =M31-M28 -> -125189.34

Sheet SCENERIO
A1: DoorDash San Francisco - Scenario Analysis
A2: Base Vs Best Case Vs Worst Case | July 2024 - June 2025
A4: SCENERIO ASSUMPTIONS
A5: Driver | B5: Worst Case | C5: Base Case | D5: Best Case | E5: Rationale
A6: Steady State Churn (Month 4+) | B6: 0.15 | C6: 0.1 | D6: 0.08 | E6: Base 10% — given in the case study Worst 15% — 50% worse than base. In a competitive market like San Francisco where Uber Eats and Skip are aggressive, research shows churn can be 1.5x higher in contested markets Best 8% — 20% better than base. DashPass subscribers historically churn at 8% steady state — so best case assumes successful DashPass conversion
A7: Competitor Additional Churn (Apr-Jun) | B7: 0.08 | C7: 0.05 | D7: 0.03 | E7: Base 5% — given in the case study Worst 8% — 60% worse than base. Competitor runs sustained promotions for 6 months not 3, maintaining elevated churn pressure Best 3% — 40% better than base. DashPass and loyalty programs switching reduce behavior — only price-sensitive customers churn
A8: Orders Per Customer Per Month | B8: 1.5 | C8: 2 | D8: 2.5 | E8: Base 2.0 — given in the case study Worst 1.5 — 25% below base. Competitor promotions cause customers to split orders between platforms — reducing DoorDash frequency Best 2.5 — 25% above base. DashPass free delivery removes friction — subscribers order 25% more frequently than non-subscribers
A9: Customer Acquisition Cost | B9: 18 | C9: 12 | D9: 10 | E9: Base $12 — given in the case study Worst $18 — 50% above base. Competitor launches aggressive paid digital acquisition in San Francisco simultaneously — bidding up Google and Meta CPCs by 50% Best $10 — 17% below base. Strong word of mouth and organic growth from DashPass referral program reduces blended CAC
A10: Delivery Fee Per Order (Normal months) | B10: 3 | C10: 3.53 | D10: 4 | E10: Base $3.53 — calculated from historical data average Worst $3.00 — 15% below base. Competitive pressure forces DoorDash to reduce delivery fees to retain price-sensitive customers Best $4.00 — 13% above base. Premium positioning and DashPass membership allows higher non-member delivery fees — consistent with DoorDash's actual pricing strategy
A12: FINANCIAL OUTCOMES — 12 MONTH SUMMARY
B13: Worst Case | C13: Base Case | D13: Best Case | E13: Delta (Best vs Worst)
A14: Total Active Customer Jun-25 | B14: 44907.056 | C14: 54707.159 | D14: 60843.376 | E14: =D14-B14 -> 15936.32
A15: Total Orders (12 months) | B15: 562761.27 | C15: 816008.87 | D15: 1065027.4 | E15: =D15-B15 -> 502266.14
A16: Total Revenue (12 months) | B16: 4730237.9 | C16: 7076613.6 | D16: 9490625.5 | E16: =D16-B16 -> 4760387.5
A17: Total Dasher Costs ( 12 months) | B17: 3690982 | C17: 5351956.9 | D17: 6985194.7 | E17: =D17-B17 -> 3294212.7
A18: Total CAC (12 months) | B18: 3348000 | C18: 2232000 | D18: 1860000 | E18: =D18-B18 -> -1488000
A19: Net Contribuition ( 12 months) | B19: -2308744.1 | C19: -507343.34 | D19: 645430.79 | E19: =D19+B19 -> -1663313.3
A20: Breakeven Month | B20: Never | C20: 45627 | D20: 45597 | E20: 2 months earlier

Sheet INSIGHT
A1: KEY SCENARIO INSIGHTS
A2: Churn is the biggest lever
B3: Reducing steady state churn from 10% to 8% adds approximately 6,100 active customers by June 2025 versus base case and improves net contribution by approximately $500k across the 12-month period. The first two months carry the highest churn risk at 30% monthly — DashPass conversion during onboarding is the single highest-impact retention investment available to the team.
A8: Competitor disruption is the biggest risk
B9: The April-June 2025 competitor shock is the single largest risk factor in this model. Escalating competitor churn from 5% to 8% combined with sustained delivery fee pressure drives an additional $1.8M in losses versus base case — moving the market from -$507K to -$2.31M net contribution over 12 months. A proactive competitive defense protocol triggered by competitor spend thresholds and targeting DashPass subscribers before churn accelerates would significantly reduce this exposure.
A15: Order frequency drives profitability faster than customer count
B16: Increasing orders per customer from 2.0 to 2.5 generates approximately 249,000 additional orders and $2.41M in incremental revenue over 12 months with zero additional acquisition cost. At a CAC range of $10-18 across scenarios, retaining and engaging existing customers is 3-5x more capital-efficient than acquiring new ones. Personalized recommendations, DashPass perks, and loyalty rewards are the highest-leverage tools available to improve this metric.
