Workbook

Sheet Assumptions
A1: FP&A Budget & Forecast Model
A2: Assumptions & Drivers
A4: Driver | B4: Value | C4: Notes
A5: REVENUE DRIVERS
A6: Monthly Customers (Base) | B6: 500 | C6: Starting customer count
A7: Monthly New Customers | B7: 20 | C7: New adds per month
A8: Monthly Churn Rate | B8: 0.02 | C8: % customers lost monthly
A9: Average Revenue Per User | B9: 150 | C9: Monthly per customer
A10: Annual Price Increase | B10: 0.03 | C10: Applied at month 12
A12: EXPENSE DRIVERS
A13: Headcount | B13: 10 | C13: Full time employees
A14: Average Salary | B14: 70000 | C14: Annual per employee
A15: Benefits & Payroll Tax | B15: 0.2 | C15: % of salary
A16: Office & Overhead | B16: 5000 | C16: Monthly fixed cost
A17: Marketing Spend | B17: 15000 | C17: Monthly
A18: Software & Tools | B18: 3000 | C18: Monthly
A19: Miscellaneous | B19: 2000 | C19: Monthly
A21: SCENARIO TOGGLE
A22: Active Scenario | B22: Downside | C22: Base / Upside / Downside
A23: Upside Revenue Multiplier | B23: 1.15 | C23: 15% above base
A24: Downside Revenue Multiplier | B24: 0.85 | C24: 15% below base

Sheet Revenue
A1: Revenue Forecast
A2: Linked to Assumptions — do not hardcode values
A4: Metric | B4: Jan | C4: Feb | D4: Mar | E4: Apr | F4: May | G4: Jun | H4: Jul | I4: Aug | J4: Sep | K4: Oct | L4: Nov | M4: Dec | N4: Full year
A5: Starting Customers | B5: =Assumptions!B6 -> 500 | C5: =B8 -> 510 | D5: =C8 -> 520 | E5: =D8 -> 530 | F5: =E8 -> 539 | G5: =F8 -> 548 | H5: =G8 -> 557 | I5: =H8 -> 566 | J5: =I8 -> 575 | ... M5: =L8 -> 599 | N5: =SUM(B5:M5) -> 6618
A6: New Customers Added | B6: =Assumptions!$B$7 -> 20 | C6: =Assumptions!$B$7 -> 20 | D6: =Assumptions!$B$7 -> 20 | E6: =Assumptions!$B$7 -> 20 | F6: =Assumptions!$B$7 -> 20 | G6: =Assumptions!$B$7 -> 20 | H6: =Assumptions!$B$7 -> 20 | I6: =Assumptions!$B$7 -> 20 | ... M6: =Assumptions!$B$7 -> 20 | N6: =SUM(B6:M6) -> 240
A7: Churned Customers | B7: =ROUND(B5*Assumptions!$B$8,0) -> 10 | C7: =ROUND(C5*Assumptions!$B$8,0) -> 10 | D7: =ROUND(D5*Assumptions!$B$8,0) -> 10 | E7: =ROUND(E5*Assumptions!$B$8,0) -> 11 | F7: =ROUND(F5*Assumptions!$B$8,0) -> 11 | G7: =ROUND(G5*Assumptions!$B$8,0) -> 11 | H7: =ROUND(H5*Assumptions!$B$8,0) -> 11 | I7: =ROUND(I5*Assumptions!$B$8,0) -> 11 | ... M7: =ROUND(M5*Assumptions!$B$8,0) -> 12 | N7: =SUM(B7:M7) -> 133
A8: Ending Customers | B8: =SUM(B5:B6)-B7 -> 510 | C8: =SUM(C5:C6)-C7 -> 520 | D8: =SUM(D5:D6)-D7 -> 530 | E8: =SUM(E5:E6)-E7 -> 539 | F8: =SUM(F5:F6)-F7 -> 548 | G8: =SUM(G5:G6)-G7 -> 557 | H8: =SUM(H5:H6)-H7 -> 566 | I8: =SUM(I5:I6)-I7 -> 575 | ... M8: =SUM(M5:M6)-M7 -> 607 | N8: =SUM(B8:M8) -> 6725
A10: Average Revenue Per User | B10: =Assumptions!$B$9 -> 150 | C10: =Assumptions!$B$9 -> 150 | D10: =Assumptions!$B$9 -> 150 | E10: =Assumptions!$B$9 -> 150 | F10: =Assumptions!$B$9 -> 150 | G10: =Assumptions!$B$9 -> 150 | H10: =Assumptions!$B$9 -> 150 | I10: =Assumptions!$B$9 -> 150 | ... M10: =Assumptions!$B$9 -> 150 | N10: =SUM(B10:M10) -> 1800
A11: Scenario Multiplier | B11: =IF(Assumptions!$B$22="Base",1,IF(Assumptions!$B$22="Upside",Assumptions!$B$23,Assumptions!$B$24)) -> 0.85 | C11: =IF(Assumptions!$B$22="Base",1,IF(Assumptions!$B$22="Upside",Assumptions!$B$23,Assumptions!$B$24)) -> 0.85 | D11: =IF(Assumptions!$B$22="Base",1,IF(Assumptions!$B$22="Upside",Assumptions!$B$23,Assumptions!$B$24)) -> 0.85 | E11: =IF(Assumptions!$B$22="Base",1,IF(Assumptions!$B$22="Upside",Assumptions!$B$23,Assumptions!$B$24)) -> 0.85 | F11: =IF(Assumptions!$B$22="Base",1,IF(Assumptions!$B$22="Upside",Assumptions!$B$23,Assumptions!$B$24)) -> 0.85 | G11: =IF(Assumptions!$B$22="Base",1,IF(Assumptions!$B$22="Upside",Assumptions!$B$23,Assumptions!$B$24)) -> 0.85 | H11: =IF(Assumptions!$B$22="Base",1,IF(Assumptions!$B$22="Upside",Assumptions!$B$23,Assumptions!$B$24)) -> 0.85 | I11: =IF(Assumptions!$B$22="Base",1,IF(Assumptions!$B$22="Upside",Assumptions!$B$23,Assumptions!$B$24)) -> 0.85 | ... M11: =IF(Assumptions!$B$22="Base",1,IF(Assumptions!$B$22="Upside",Assumptions!$B$23,Assumptions!$B$24)) -> 0.85 | N11: =SUM(B11:M11) -> 10.2
A13: Monthly Revenue | B13: =B8*B10*B11 -> 65025 | C13: =C8*C10*C11 -> 66300 | D13: =D8*D10*D11 -> 67575 | E13: =E8*E10*E11 -> 68722.5 | F13: =F8*F10*F11 -> 69870 | G13: =G8*G10*G11 -> 71017.5 | H13: =H8*H10*H11 -> 72165 | I13: =I8*I10*I11 -> 73312.5 | ... M13: =M8*M10*M11 -> 77392.5 | N13: =SUM(B13:M13) -> 857437.5
A16: MoM Revenue Growth % | B16: =ROUND(((C13-B13)/B13),2) -> 0.02 | C16: =ROUND(((D13-C13)/C13),2) -> 0.02 | D16: =ROUND(((E13-D13)/D13),2) -> 0.02 | E16: =ROUND(((F13-E13)/E13),2) -> 0.02 | F16: =ROUND(((G13-F13)/F13),2) -> 0.02 | G16: =ROUND(((H13-G13)/G13),2) -> 0.02 | H16: =ROUND(((I13-H13)/H13),2) -> 0.02 | I16: =ROUND(((J13-I13)/I13),2) -> 0.01 | ... M16: =ROUND(((N13-M13)/M13),2) -> 10.08 | N16: =SUM(B16:M16) -> 10.26

Sheet Expenses
A1: Expense Forecast
A2: Linked to Assumptions — do not hardcode values
A4: Expense Item | B4: Jan | C4: Feb | D4: Mar | E4: Apr | F4: May | G4: Jun | H4: Jul | I4: Aug | J4: Sep | K4: Oct | L4: Nov | M4: Dec | N4: Full Year
A5: PEOPLE COSTS
A6: Gross Salary Cost | B6: =Assumptions!$B$14*Assumptions!$B$13/12 -> 58333.333 | C6: =Assumptions!$B$14*Assumptions!$B$13/12 -> 58333.333 | D6: =Assumptions!$B$14*Assumptions!$B$13/12 -> 58333.333 | E6: =Assumptions!$B$14*Assumptions!$B$13/12 -> 58333.333 | F6: =Assumptions!$B$14*Assumptions!$B$13/12 -> 58333.333 | G6: =Assumptions!$B$14*Assumptions!$B$13/12 -> 58333.333 | H6: =Assumptions!$B$14*Assumptions!$B$13/12 -> 58333.333 | I6: =Assumptions!$B$14*Assumptions!$B$13/12 -> 58333.333 | ... M6: =Assumptions!$B$14*Assumptions!$B$13/12 -> 58333.333 | N6: =SUM(B6:M6) -> 700000
A7: Benefits & Payroll Tax | B7: =B6*Assumptions!$B$15 -> 11666.667 | C7: =C6*Assumptions!$B$15 -> 11666.667 | D7: =D6*Assumptions!$B$15 -> 11666.667 | E7: =E6*Assumptions!$B$15 -> 11666.667 | F7: =F6*Assumptions!$B$15 -> 11666.667 | G7: =G6*Assumptions!$B$15 -> 11666.667 | H7: =H6*Assumptions!$B$15 -> 11666.667 | I7: =I6*Assumptions!$B$15 -> 11666.667 | ... M7: =M6*Assumptions!$B$15 -> 11666.667 | N7: =SUM(B7:M7) -> 140000
A8: Total People Cost | B8: =B6+B7 -> 70000 | C8: =C6+C7 -> 70000 | D8: =D6+D7 -> 70000 | E8: =E6+E7 -> 70000 | F8: =F6+F7 -> 70000 | G8: =G6+G7 -> 70000 | H8: =H6+H7 -> 70000 | I8: =I6+I7 -> 70000 | ... M8: =M6+M7 -> 70000 | N8: =SUM(B8:M8) -> 840000
A10: OPERATING COSTS
A11: Office & Overhead | B11: =Assumptions!$B$16 -> 5000 | C11: =Assumptions!$B$16 -> 5000 | D11: =Assumptions!$B$16 -> 5000 | E11: =Assumptions!$B$16 -> 5000 | F11: =Assumptions!$B$16 -> 5000 | G11: =Assumptions!$B$16 -> 5000 | H11: =Assumptions!$B$16 -> 5000 | I11: =Assumptions!$B$16 -> 5000 | ... M11: =Assumptions!$B$16 -> 5000 | N11: =SUM(B11:M11) -> 60000
A12: Marketing Spend | B12: =Assumptions!$B$17 -> 15000 | C12: =Assumptions!$B$17 -> 15000 | D12: =Assumptions!$B$17 -> 15000 | E12: =Assumptions!$B$17 -> 15000 | F12: =Assumptions!$B$17 -> 15000 | G12: =Assumptions!$B$17 -> 15000 | H12: =Assumptions!$B$17 -> 15000 | I12: =Assumptions!$B$17 -> 15000 | ... M12: =Assumptions!$B$17 -> 15000 | N12: =SUM(B12:M12) -> 180000
A13: Software & Tools | B13: =Assumptions!$B$18 -> 3000 | C13: =Assumptions!$B$18 -> 3000 | D13: =Assumptions!$B$18 -> 3000 | E13: =Assumptions!$B$18 -> 3000 | F13: =Assumptions!$B$18 -> 3000 | G13: =Assumptions!$B$18 -> 3000 | H13: =Assumptions!$B$18 -> 3000 | I13: =Assumptions!$B$18 -> 3000 | ... M13: =Assumptions!$B$18 -> 3000 | N13: =SUM(B13:M13) -> 36000
A14: Miscellaneous | B14: =Assumptions!$B$19 -> 2000 | C14: =Assumptions!$B$19 -> 2000 | D14: =Assumptions!$B$19 -> 2000 | E14: =Assumptions!$B$19 -> 2000 | F14: =Assumptions!$B$19 -> 2000 | G14: =Assumptions!$B$19 -> 2000 | H14: =Assumptions!$B$19 -> 2000 | I14: =Assumptions!$B$19 -> 2000 | ... M14: =Assumptions!$B$19 -> 2000 | N14: =SUM(B14:M14) -> 24000
A15: Total Operating Costs | B15: =SUM(B11:B14) -> 25000 | C15: =SUM(C11:C14) -> 25000 | D15: =SUM(D11:D14) -> 25000 | E15: =SUM(E11:E14) -> 25000 | F15: =SUM(F11:F14) -> 25000 | G15: =SUM(G11:G14) -> 25000 | H15: =SUM(H11:H14) -> 25000 | I15: =SUM(I11:I14) -> 25000 | ... M15: =SUM(M11:M14) -> 25000 | N15: =SUM(B15:M15) -> 300000
A17: TOTAL EXPENSES | B17: =B8+B15 -> 95000 | C17: =C8+C15 -> 95000 | D17: =D8+D15 -> 95000 | E17: =E8+E15 -> 95000 | F17: =F8+F15 -> 95000 | G17: =G8+G15 -> 95000 | H17: =H8+H15 -> 95000 | I17: =I8+I15 -> 95000 | ... M17: =M8+M15 -> 95000 | N17: =SUM(B17:M17) -> 1140000

Sheet Forecast Summary
A1: Forecast Summary
A2: =IF(Assumptions!B22="Base","Base Case Scenario",IF(Assumptions!B22="Upside","Upside Scenario","Downside Scenario")) -> Downside Scenario
A4: P&L Summary | B4: Jan | C4: Feb | D4: Mar | E4: Apr | F4: May | G4: Jun | H4: Jul | I4: Aug | J4: Sep | K4: Oct | L4: Nov | M4: Dec | N4: Full Year
A6: Total Revenue | B6: =Revenue!B13 -> 65025 | C6: =Revenue!C13 -> 66300 | D6: =Revenue!D13 -> 67575 | E6: =Revenue!E13 -> 68722.5 | F6: =Revenue!F13 -> 69870 | G6: =Revenue!G13 -> 71017.5 | H6: =Revenue!H13 -> 72165 | I6: =Revenue!I13 -> 73312.5 | ... M6: =Revenue!M13 -> 77392.5 | N6: =SUM(B6:M6) -> 857437.5
A7: Total Expenses | B7: =Expenses!B17 -> 95000 | C7: =Expenses!C17 -> 95000 | D7: =Expenses!D17 -> 95000 | E7: =Expenses!E17 -> 95000 | F7: =Expenses!F17 -> 95000 | G7: =Expenses!G17 -> 95000 | H7: =Expenses!H17 -> 95000 | I7: =Expenses!I17 -> 95000 | ... M7: =Expenses!M17 -> 95000 | N7: =SUM(B7:M7) -> 1140000
A9: Gross Profit | B9: =B6-B7 -> -29975 | C9: =C6-C7 -> -28700 | D9: =D6-D7 -> -27425 | E9: =E6-E7 -> -26277.5 | F9: =F6-F7 -> -25130 | G9: =G6-G7 -> -23982.5 | H9: =H6-H7 -> -22835 | I9: =I6-I7 -> -21687.5 | ... N9: =N6-N7 -> -282562.5
A10: Profit Margin % | B10: =ROUND((B9/B6),2) -> -0.46 | C10: =ROUND((C9/C6),2) -> -0.43 | D10: =ROUND((D9/D6),2) -> -0.41 | E10: =ROUND((E9/E6),2) -> -0.38 | F10: =ROUND((F9/F6),2) -> -0.36 | G10: =ROUND((G9/G6),2) -> -0.34 | H10: =ROUND((H9/H6),2) -> -0.32 | I10: =ROUND((I9/I6),2) -> -0.3 | ... M10: =ROUND((M9/M6),2) -> -0.23 | N10: =ROUND((N9/N6),3) -> -0.33
A12: People Cost % of Revenue | B12: =ROUND((Expenses!B8/B6),2) -> 1.08 | C12: =ROUND((Expenses!C8/C6),2) -> 1.06 | D12: =ROUND((Expenses!D8/D6),2) -> 1.04 | E12: =ROUND((Expenses!E8/E6),2) -> 1.02 | F12: =ROUND((Expenses!F8/F6),2) -> 1 | G12: =ROUND((Expenses!G8/G6),2) -> 0.99 | H12: =ROUND((Expenses!H8/H6),2) -> 0.97 | I12: =ROUND((Expenses!I8/I6),2) -> 0.95 | ... N12: =ROUND((Expenses!N8/N6),2) -> 0.98
A13: Operating Cost % of Revenue | B13: =ROUND((Expenses!B15/B6),2) -> 0.38 | C13: =ROUND((Expenses!C15/C6),2) -> 0.38 | D13: =ROUND((Expenses!D15/D6),2) -> 0.37 | E13: =ROUND((Expenses!E15/E6),2) -> 0.36 | F13: =ROUND((Expenses!F15/F6),2) -> 0.36 | G13: =ROUND((Expenses!G15/G6),2) -> 0.35 | H13: =ROUND((Expenses!H15/H6),2) -> 0.35 | I13: =ROUND((Expenses!I15/I6),2) -> 0.34 | ... N13: =ROUND((Expenses!N15/N6),2) -> 0.35
A15: CUSTOMER METRICS
A16: Ending Customers | B16: =Revenue!B8 -> 510 | C16: =Revenue!C8 -> 520 | D16: =Revenue!D8 -> 530 | E16: =Revenue!E8 -> 539 | F16: =Revenue!F8 -> 548 | G16: =Revenue!G8 -> 557 | H16: =Revenue!H8 -> 566 | I16: =Revenue!I8 -> 575 | ... M16: =Revenue!M8 -> 607 | N16: =Revenue!M8 -> 607
A17: Revenue Per Customer | B17: =B6/B16 -> 127.5 | C17: =C6/C16 -> 127.5 | D17: =D6/D16 -> 127.5 | E17: =E6/E16 -> 127.5 | F17: =F6/F16 -> 127.5 | G17: =G6/G16 -> 127.5 | H17: =H6/H16 -> 127.5 | I17: =I6/I16 -> 127.5 | ... N17: =N6/N16 -> 1412.5824
A19: ANNUAL SUMMARY
A20: Full Year Revenue | B20: =N6 -> 857437.5
A21: Full Year Expenses | B21: =N7 -> 1140000
A22: Full Year Profit | B22: =N9 -> -282562.5
A23: Full Year Margin % | B23: =N10 -> -0.33

Sheet Scenarios
A1: Scenario Analysis Summary
A2: Base vs Upside vs Downside — Full Year View
A4: Metric | B4: Upside (+15%) | C4: Base Case | D4: Downside (-15%) | E4: Upside vs Downside Gap
A6: REVENUE
A7: Full Year Revenue | B7: 1160063 | C7: 1008750 | D7: 857438 | E7: =B7-D7 -> 302625
A8: Revenue vs Base Case | B8: =B7-C7 -> 151313 | C8: - | D8: =D7-C7 -> -151312
A9: Revenue Variance vs Base % | B9: =ROUND((B8/C7),2) -> 0.15 | C9: - | D9: =ROUND((D8/C7),2) -> -0.15
A11: PROFITABILITY
A12: Full Year Expenses | B12: 1140000 | C12: 1140000 | D12: 1140000 | E12: =B12-D12 -> 0
A13: Full Year Profit / (Loss) | B13: =B7-B12 -> 20063 | C13: =C7-C12 -> -131250 | D13: =D7-D12 -> -282562 | E13: =B13-D13 -> 302625
A14: Profit Margin % | B14: =ROUND((B13/B7),2) -> 0.02 | C14: =ROUND((C13/C7),2) -> -0.13 | D14: =ROUND((D13/D7),2) -> -0.33 | E14: =B14-D14 -> 0.35
A16: CUSTOMERS
A17: Year End Customers | B17: 607 | C17: 607 | D17: 607 | E17: =B17-D17 -> 0
A18: Annual Revenue Per Customer | B18: =ROUND((B7/B17),2) -> 1911.14 | C18: =ROUND((C7/C17),2) -> 1661.86 | D18: =ROUND((D7/D17),2) -> 1412.58 | E18: =B18-D18 -> 498.56
A20: KEY INSIGHTS
A21: Breakeven Scenario | B21: Upside Only | C21: Not Achieved | D21: Not Achieved
A22: Revenue Gap to Breakeven | B22: - | C22: =C12-C7 -> 131250 | D22: =D12-D7 -> 282562
A23: Expense Reduction Needed to Breakeven | B23: - | C23: =ABS(C7-C12) -> 131250 | D23: =ABS(D7-D12) -> 282562
A25: RECOMMENDATION
A26: The business only achieves profitability under Upside assumptions. Leadership should prioritize revenue growth strategies and evaluate cost reduction opportunities to improve Base case viability.
