Workbook

Sheet ASSUMPTIONS
A1: Ontario Power Generation — Financial Performance & Variance Analysis Model | B1: 2021A | C1: 2022A | D1: 2023A | E1: SOURCE
A2: Source: OPG Annual Reports 2021-2023 | Budget assumptions derived from management guidance
A4: HISTORICAL ACTUALS — OPG Annual Report Data
A5: Total Revenue ($M) | B5: 6800 | C5: 7200 | D5: 7400 | E5: OPG Annual Report
A6: EBIT ($M) | B6: 2100 | C6: 2170 | D6: 2198 | E6: OPG Annual Report
A7: Net Income | B7: 1325 | C7: 1636 | D7: 1741 | E7: OPG Annual Report
A8: EBIT Margin % | B8: =B6/B5 -> 0.30882353 | C8: =C6/C5 -> 0.30138889 | D8: =D6/D5 -> 0.29702703 | E8: Derived
A9: Net Income Margin % | B9: =B7/B5 -> 0.19485294 | C9: =C7/C5 -> 0.22722222 | D9: =D7/D5 -> 0.23527027 | E9: Derived
A10: Revenue YoY Growth % | B10: - | C10: =(C5-B5)/B5 -> 0.058823529 | D10: =(D5-C5)/C5 -> 0.027777778 | E10: Derived
A11: Net Income YoY Growth % | B11: - | C11: =(C7-B7)/B7 -> 0.23471698 | D11: =(D7-C7)/C7 -> 0.064180929 | E11: Derived
A13: REVENUE BY SEGMENT ($M)
A15: Regulated Nuclear Generation | B15: 3900 | C15: 4200 | D15: 4500 | E15: OPG Annual Report
A16: Regulated Hydroelectric | B16: 2000 | C16: 2100 | D16: 2100 | E16: OPG Annual Report
A17: Contracted & Other | B17: 900 | C17: 900 | D17: 800 | E17: OPG Annual Report
A18: Total Revenue Check ($M) | B18: =SUM(B15:B17) -> 6800 | C18: =SUM(C15:C17) -> 7200 | D18: =SUM(D15:D17) -> 7400 | E18: Derived
A19: Nuclear % of Revenue | B19: =B15/B$18 -> 0.57352941 | C19: =C15/C$18 -> 0.58333333 | D19: =D15/D$18 -> 0.60810811 | E19: Derived
A20: Hydro % of Revenue | B20: =B16/B$18 -> 0.29411765 | C20: =C16/C$18 -> 0.29166667 | D20: =D16/D$18 -> 0.28378378 | E20: Derived
A21: Contracted & Other % of Revenue | B21: =B17/B$18 -> 0.13235294 | C21: =C17/C$18 -> 0.125 | D21: =D17/D$18 -> 0.10810811 | E21: Derived
A23: 2024 BUDGET ASSUMPTIONS
A24: Note: "Budget assumptions are analyst estimates derived from OPG historical growth trends and publicly available management guidance. In practice these figures would be sourced directly from OPG's internal planning systems (SAP BPC). Figures are for modeling demonstration purposes only."
A25: Driver | B25: Budget | C25: Forecast (Mid-Year) | E25: Derivation
A26: Revenue Growth % vs 2023 | B26: 0.035 | C26: 0.028 | E26: Historical avg growth + management guidance
A27: Budget Revenue ($M) | B27: =D5*(1+B26) -> 7659 | C27: =D5*(1+C26) -> 7607.2 | E27: 2023A × (1 + growth rate)
A28: EBIT Margin % Target | B28: 0.305 | C28: 0.298 | E28: Historical margin trend continuation
A29: Budget EBIT ($M) | B29: =B27*B28 -> 2335.995 | C29: =C27*C28 -> 2266.9456 | E29: Revenue × EBIT Margin %
A30: Net Income Margin % Target | B30: 0.24 | C30: 0.235 | E30: Historical margin trend continuation
A31: Budget Net Income ($M) | B31: =B27*B30 -> 1838.16 | C31: =C27*C30 -> 1787.692 | E31: Revenue × Net Income Margin %
A33: SEGMENT BUDGET ASSUMPTIONS ($M)
A34: Segment | B34: 2023A | C34: 2024 Budget | D34: 2024 Forecast | E34: Growth Assumption
A35: Regulated Nuclear | B35: 4500 | C35: 4800 | D35: 4650 | E35: +6.7% budget / +3.3% forecast — refurbishment capacity | F35: Darlington Refurbishment adds capacity — units coming back online increase generation revenue
A36: Regulated Hydro | B36: 2100 | C36: 2150 | D36: 2080 | E36: +2.4% budget / -1.0% forecast — water levels | F36: Flat historically — slight increase assuming normal water levels
A37: Contracted & Other | B37: 800 | C37: 820 | D37: 780 | E37: +2.5% budget / -2.5% forecast — contract renewals | F37: Small contracts renewing at similar rates
A38: Total Budget Revenue ($M) | B38: =SUM(B35:B37) -> 7400 | C38: =SUM(C35:C37) -> 7770 | D38: =SUM(D35:D37) -> 7510

Sheet VARIANCE ANALYSIS
A1: OPG — Variance Analysis Report
A2: Actuals vs Budget vs Prior Year | FY2023
A4: Financial Metric | B4: 2022A | C4: 2023A | D4: 2024 Budget | E4: Variance $(Act vs Bud) | F4: Variance % (Act vs Bud) | G4: Variance $ (YoY) | H4: Variance Driver
A5: REVENUE
A6: Total Revenue ($M) | B6: =ASSUMPTIONS!C5 -> 7200 | C6: =ASSUMPTIONS!D5 -> 7400 | D6: =ASSUMPTIONS!B27 -> 7659 | E6: =C6-D6 -> -259 | F6: =E6/D6 -> -0.033816425 | G6: =C6-B6 -> 200 | H6: Nuclear regulated price increase + higher generation output
A7: Regulated Nuclear ($M) | B7: =ASSUMPTIONS!C15 -> 4200 | C7: =ASSUMPTIONS!D15 -> 4500 | D7: =ASSUMPTIONS!C35 -> 4800 | E7: =C7-D7 -> -300 | F7: =E7/D7 -> -0.0625 | G7: =C7-B7 -> 300 | H7: Darlington refurbishment capacity + regulated price adjustments
A8: Regulated Hydro ($M) | B8: =ASSUMPTIONS!C16 -> 2100 | C8: =ASSUMPTIONS!D16 -> 2100 | D8: =ASSUMPTIONS!C36 -> 2150 | E8: =C8-D8 -> -50 | F8: =E8/D8 -> -0.023255814 | G8: =C8-B8 -> 0 | H8: Water levels — flat vs prior year
A9: Contracted & Other ($M) | B9: =ASSUMPTIONS!C17 -> 900 | C9: =ASSUMPTIONS!D17 -> 800 | D9: =ASSUMPTIONS!C37 -> 820 | E9: =C9-D9 -> -20 | F9: =E9/D9 -> -0.024390244 | G9: =C9-B9 -> -100 | H9: Contract renewals — volume decline
A11: PROFITABILITY
A12: EBIT ($M) | B12: =ASSUMPTIONS!C6 -> 2170 | C12: =ASSUMPTIONS!D6 -> 2198 | D12: =ASSUMPTIONS!B29 -> 2335.995 | E12: =C12-D12 -> -137.995 | F12: =E12/D12 -> -0.059073328 | G12: =C12-B12 -> 28 | H12: Revenue growth partially offset by higher operating costs
A13: EBIT Margin % | B13: =ASSUMPTIONS!C8 -> 0.30138889 | C13: =ASSUMPTIONS!D8 -> 0.29702703 | D13: =ASSUMPTIONS!B28 -> 0.305 | E13: =C13-D13 -> -0.007972973 | G13: =C13-B13 -> -0.0043618619 | H13: Margin compression from cost pressures
A14: Net Income ($M) | B14: =ASSUMPTIONS!C7 -> 1636 | C14: =ASSUMPTIONS!D7 -> 1741 | D14: =ASSUMPTIONS!B31 -> 1838.16 | E14: =C14-D14 -> -97.16 | F14: =E14/D14 -> -0.052857205 | G14: =C14-B14 -> 105 | H14: Strong earnings growth driven by regulated nuclear performance
A15: Net Income Margin % | B15: =ASSUMPTIONS!C9 -> 0.22722222 | C15: =ASSUMPTIONS!D9 -> 0.23527027 | D15: =ASSUMPTIONS!B30 -> 0.24 | E15: =C15-D15 -> -0.0047297297 | F15: =E15/D15 -> -0.019707207 | G15: =C15-B15 -> 0.008048048 | H15: Margin expansion from operating leverage
A17: VARIANCE SUMMARY
A18: Total Revenue Variance vs Budget | B18: =E6 -> -259 | C18: =F6 -> -0.033816425
A19: Net Income Variance vs Budget | B19: =E14 -> -97.16 | C19: =F14 -> -0.052857205
A20: YoY Revenue Growth | B20: =G6/B6 -> 0.027777778
A21: YoY Net Income Growth | B21: =G14/B14 -> 0.064180929

Sheet SEGMENT PERFORMANCE
A1: OPG — Segment Performance Analysis
A2: Revenue and contribution by business segment | 2021-2023 Actuals + 2024 Budget
A4: Segment Metric | B4: 2021A | C4: 2022A | D4: 2023A | E4: 2024 Budget | F4: 3-year CAGR
A5: REVENUE ($M)
A6: Regulated Nuclear | B6: =ASSUMPTIONS!B15 -> 3900 | C6: =ASSUMPTIONS!C15 -> 4200 | D6: =ASSUMPTIONS!D15 -> 4500 | E6: =ASSUMPTIONS!C35 -> 4800 | F6: =(D6/B6)^(1/3)-1 -> 0.048856246
A7: Regulated Hydro | B7: =ASSUMPTIONS!B16 -> 2000 | C7: =ASSUMPTIONS!C16 -> 2100 | D7: =ASSUMPTIONS!D16 -> 2100 | E7: =ASSUMPTIONS!C36 -> 2150 | F7: =(D7/B7)^(1/3)-1 -> 0.016396357
A8: Contracted & Other | B8: =ASSUMPTIONS!B17 -> 900 | C8: =ASSUMPTIONS!C17 -> 900 | D8: =ASSUMPTIONS!D17 -> 800 | E8: =ASSUMPTIONS!C37 -> 820 | F8: =(D8/B8)^(1/3)-1 -> -0.038500286
A9: Total Revenue | B9: =SUM(B6:B8) -> 6800 | C9: =SUM(C6:C8) -> 7200 | D9: =SUM(D6:D8) -> 7400 | E9: =SUM(E6:E8) -> 7770 | F9: =SUM(F6:F8) -> 0.026752317
A11: REVENUE MIX %
A12: Nuclear % of Total | B12: =B6/B$9 -> 0.57352941 | C12: =C6/C$9 -> 0.58333333 | D12: =D6/D$9 -> 0.60810811 | E12: =E6/E$9 -> 0.61776062
A13: Hydro % of Total | B13: =B7/B$9 -> 0.29411765 | C13: =C7/C$9 -> 0.29166667 | D13: =D7/D$9 -> 0.28378378 | E13: =E7/E$9 -> 0.27670528
A14: Contracted % of Total | B14: =B8/B$9 -> 0.13235294 | C14: =C8/C$9 -> 0.125 | D14: =D8/D$9 -> 0.10810811 | E14: =E8/E$9 -> 0.10553411
A15: Mix Check (should = 100%) | B15: =SUM(B12:B14) -> 1 | C15: =SUM(C12:C14) -> 1 | D15: =SUM(D12:D14) -> 1 | E15: =SUM(E12:E14) -> 1
A17: REVENUE GROWTH % YoY
A18: Nuclear YoY Growth | B18: - | C18: =(C6-B6)/B6 -> 0.076923077 | D18: =(D6-C6)/C6 -> 0.071428571 | E18: =(E6-D6)/D6 -> 0.066666667
A19: Hydro YoY Growth | B19: - | C19: =(C7-B7)/B7 -> 0.05 | D19: =(D7-C7)/C7 -> 0 | E19: =(E7-D7)/D7 -> 0.023809524
A20: Contracted YoY Growth | B20: - | C20: =(C8-B8)/B8 -> 0 | D20: =(D8-C8)/C8 -> -0.11111111 | E20: =(E8-D8)/D8 -> 0.025
A21: Total Revenue Growth | B21: - | C21: =(C9-B9)/B9 -> 0.058823529 | D21: =(D9-C9)/C9 -> 0.027777778 | E21: =(E9-D9)/D9 -> 0.05
A23: SEGMENT CONTRIBUTION TO REVENUE CHANGE ($M)
A24: Segment | B24: 2022 vs 2021 ($M) | C24: 2023 vs 2022 ($M) | D24: % of Total Change
A25: Nuclear | B25: =C6-B6 -> 300 | C25: =D6-C6 -> 300 | D25: =C25/C28 -> 1.5
A26: Hydro | B26: =C7-B7 -> 100 | C26: =D7-C7 -> 0 | D26: =C26/C28 -> 0
A27: Contracted | B27: =C8-B8 -> 0 | C27: =D8-C8 -> -100 | D27: =C27/C28 -> -0.5
A28: Total Change | B28: =C9-B9 -> 400 | C28: =D9-C9 -> 200 | D28: =SUM(D25:D27) -> 1
A30: KEY SEGMENT METRICS
A31: Largest Revenue Segment | B31: Nuclear | C31: Nuclear | D31: Nuclear | E31: Nuclear
A32: Nuclear % of Total Revenue | D32: Nuclear (+7.1%) | E32: Nuclear (+6.7% budget)
A33: Fastest Growing Segment (YoY) | D33: Nuclear (+7.1%) | E33: Nuclear (+6.7% budget)
A34: Declining Segment | D34: Contracted (-11.1%) | E34: Contracted (+2.5% recovery budgeted)

Sheet INSIGHTS
A1: OPG — Analyst Insights & Financial Commentary
A2: Based on OPG Annual Reports 2021-2023 | Prepared by Dabi C. Njere, Financial Analyst
A4: 1. BUSINESS OVERVIEW
A5: Ontario Power Generation is Ontario's largest clean electricity generator, producing approximately half of the province's power through regulated nuclear, regulated hydroelectric, and contracted generation assets. As a Crown corporation wholly owned by the Province of Ontario, OPG operates under a regulated rate framework set by the Ontario Energy Board — meaning revenue is largely determined by approved regulated prices and generation volumes rather than market competition. This regulated structure creates a stable, predictable revenue base but also means that variances from budget are primarily driven by generation output, planned outage timing, and regulatory rate decisions rather than commercial pricing dynamics.
A7: 2. REVENUE PERFORMANCE 2021-2023
A8: OPG's total revenue grew from approximately $6,800M in 2021 to $7,400M in 2023 — a 3-year CAGR of approximately 4.3%. This growth was driven almost entirely by the Regulated Nuclear Generation segment, which expanded from $3,900M to $4,500M over the same period, reflecting the progressive return of refurbished Darlington units to service and OEB-approved regulated price adjustments. The Regulated Hydro segment remained essentially flat at approximately $2,100M — consistent with the segment's dependence on water levels and stable long-term contracts. The Contracted & Other segment declined from $900M to $800M, reflecting contract expiries and volume reductions. Nuclear now represents approximately 61% of total revenue, up from 57% in 2021 — highlighting the increasing concentration of OPG's revenue base in its largest regulated segment.
A10: 3. PROFITABILITY & MARGIN ANALYSIS
A11: Net income grew strongly from $1,325M in 2021 to $1,741M in 2023 — a 3-year increase of 31.4%. EBIT expanded from approximately $2,100M to $2,198M over the same period, though EBIT growth was more modest at 4.7% reflecting rising operating costs associated with the Darlington Refurbishment Project. Net income growth significantly outpaced EBIT growth, suggesting favorable movements in financing costs or deferred tax recoveries below the operating line. EBIT margin compressed slightly from approximately 30.9% in 2021 to 29.7% in 2023 — a trend consistent with higher capital project costs flowing through the income statement. Despite this compression, OPG's margins remain strong and reflect the financial advantages of operating regulated assets with cost recovery mechanisms embedded in the rate structure.
A13: 4. KEY VARIANCE FINDINGS
A14: The variance analysis reveals that Nuclear Generation is the single most significant driver of OPG's financial performance — both in terms of absolute revenue contribution and year-over-year change. In 2023 the Nuclear segment contributed $300M of incremental revenue versus 2022, accounting for the entirety of OPG's revenue growth and offsetting the $100M decline in Contracted & Other revenue. The Hydro segment contributed zero incremental revenue in 2023 — flat water levels and stable contracts produced consistent but unchanged output. From a budget perspective the 2024 budget assumes continued nuclear growth of 6.7% driven by Darlington refurbishment capacity coming back online. The primary variance risk is generation volume — any unplanned outage or regulatory delay in returning refurbished units to service would directly impact revenue and net income, as demonstrated by the planned 2024 outage on Unit 2 which reduced net income by $753M versus 2023.
A16: 5. DARLINGTON REFURBISHMENT — FP&A IMPLICATIONS
A17: The Darlington Refurbishment Project — budgeted at $12.8B and on track for completion in 2026 — is the most significant financial planning variable in OPG's medium-term outlook. From an FP&A perspective the refurbishment creates predictable but significant short-term earnings volatility: each unit taken offline for refurbishment reduces nuclear generation volume and revenue for the duration of the outage, while refurbishment costs flow through capital expenditure. Unit 1 returned to full power in late 2024 approximately five months ahead of schedule — a positive variance against the refurbishment plan. Unit 4, the final unit, is on track for 2026 completion. The financial planning team must model outage timing assumptions carefully — a one-month acceleration or delay in refurbishment completion has material revenue implications given nuclear's 61% share of total revenue. This dynamic makes OPG's budget process highly sensitive to generation volume assumptions and makes variance explanation a critical recurring FP&A deliverable.
... A23: OPG Annual Reports 2021, 2022, 2023 — Ontario Power Generation Inc. OPG Q4 2024 Financial Results Press Release — March 4, 2025. Ontario Energy Board regulated rate decisions — OEB.ca. Ontario Ministry of Energy Published Plans and Annual Reports 2023-2024. All figures in Canadian dollars (CAD millions) unless otherwise stated.
